src/weight_stationary/reLU.sv
`default_nettype none

module reLU #(
    parameter DATA_WIDTH = 8
)(
    input wire clk,
    input wire nrst, 

    input wire reLU_iv,
    input wire signed [DATA_WIDTH-1:0] neuron_i,

    output logic reLU_ov,
    output logic signed [DATA_WIDTH-1:0] reLU_od
);

    always_ff @(posedge clk or negedge nrst) begin
        if(~nrst) begin
            reLU_ov <= 1'b0;
            reLU_od <= 0;
        end
        else if(reLU_iv) begin
            reLU_ov <= 1'b1;
            reLU_od <= (neuron_i>={(DATA_WIDTH){1'sd0}})? neuron_i : 0;
        end
        else begin
            reLU_ov <= 1'b0;
            reLU_od <= 0;
        end
    end   

endmodule

`default_nettype wire

src/weight_stationary/multiport_adder.sv
`default_nettype none

//pipe line 3 adder
module multiport_adder3 #(
    parameter WIDTH = 19
)(
    input wire clk,
    input wire nrst,

    input wire port_iv,
    input wire signed [3-1:0][WIDTH-1:0] port_id,

    output logic sum_ov,
    output logic signed [WIDTH-1:0] sum_od
);

    logic signed [1:0][WIDTH-1:0] sum_r;
    logic signed [1:0] port_iv_pipe;
    logic signed [WIDTH-1:0] port_id_pipe;

    // verify
    logic signed [WIDTH-1:0] sum_r0, sum_r1;
    assign {sum_r1, sum_r0} = sum_r;

    always_ff @(posedge clk or negedge nrst) begin
        if(~nrst) port_id_pipe <= 0;
        else port_id_pipe <= port_id[2];
    end

    always_ff @(posedge clk or negedge nrst) begin
        if(~nrst) port_iv_pipe <= 0;
        else begin
            port_iv_pipe[0] <= port_iv;
            port_iv_pipe[1] <= port_iv_pipe[0];
        end
    end  

    always_ff @(posedge clk or negedge nrst) begin
        if(~nrst) sum_r <= 0;
        else begin
            sum_r[0] <= (port_iv) ? (port_id[0]+port_id[1]) : 0;
            sum_r[1] <= (port_iv_pipe[0]) ? (sum_r[0]+port_id_pipe) : 0;
        end 
    end 

    assign sum_ov = port_iv_pipe[1];
    assign sum_od = sum_r[1];

endmodule

`default_nettype wire

src/weight_stationary/bias_adder.sv
`default_nettype none

module bias_adder #(
    parameter BIAS = 8'd0,
    parameter PSUM_WIDTH = 19,
    parameter DATA_WIDTH = 8,
    parameter SA_COL = 3
)(
    input wire clk,
    input wire nrst, 

    input wire bias_adder_iv,
    input wire signed [SA_COL-1:0][PSUM_WIDTH-1:0] psum_i,

    output logic biased_ov,
    output logic signed [DATA_WIDTH-1:0] biased_od
);

    logic psum_sv;
    logic [PSUM_WIDTH-1:0] psum_sd;
    logic [PSUM_WIDTH-1:0] psum_sd_shifted;


    multiport_adder3#(
        .WIDTH        ( PSUM_WIDTH )
    )u_multiport_adder(
        .clk     ( clk          ),
        .nrst    ( nrst     ),
        .port_iv ( bias_adder_iv      ),
        .port_id  ( psum_i         ),
        .sum_ov  ( psum_sv ),
        .sum_od   ( psum_sd  )
    );

    assign psum_sd_shifted = (psum_sd >>> 7);

    always_ff @(posedge clk or negedge nrst) begin
        if(~nrst) begin
            biased_ov <= 1'b0;
            biased_od <= 0;
        end
        else if(psum_sv) begin
            biased_ov <= 1'b1;
            biased_od <= (psum_sd >>> 7) + BIAS;
        end
        else begin
            biased_ov <= 1'b0;
            biased_od <= 0;
        end
    end   

endmodule

`default_nettype wire

src/weight_stationary/weight_kernel_conv0.sv
`default_nettype none
`timescale 1ns/1ps

// A:m*l, B:l*n, AB:m*n
module weight_kernel_conv0 #(
    parameter KERNEL_WIDTH = 3,
    parameter KERNEL_HEIGHT = 3,
    parameter WEIGHT_WIDTH = 8
)(
    output logic signed [KERNEL_HEIGHT-1:0][KERNEL_WIDTH-1:0][WEIGHT_WIDTH-1:0] weight_o
);

    /*
    00 01 02
    10 11 12
    20 21 22
    */
    assign weight_o = {8'sb00100000, 8'sb00100000, 8'sb00100000,
                       8'sb00100000, 8'sb00100000, 8'sb00100000,
                       8'sb00100000, 8'sb00100000, 8'sb00100000 }; // 22, 21, 20, 12, 11, 10, 02, 01, 00

endmodule 

`default_nettype wire

src/weight_stationary/PE_weight_stationary.sv
`default_nettype none
`timescale 1ns/1ps

module PE_weight_stationary #(
    parameter IFMAP_WIDTH = 8,
    parameter WEIGHT_WIDTH = 8,
    parameter ACCUMULATION_WIDTH = 3, // since 8x8*8x8, log2(8)=3 to avoid overflow
    parameter PSUM_WIDTH = IFMAP_WIDTH + WEIGHT_WIDTH + ACCUMULATION_WIDTH
)(
    input wire clk,
    input wire nrst,

    input wire signed [IFMAP_WIDTH-1:0]  ifmap_i,
    input wire signed [PSUM_WIDTH-1:0]   psum_i,
    input wire signed [WEIGHT_WIDTH-1:0] weight_i,
    input wire pe_en,

    output logic signed [IFMAP_WIDTH-1:0]  ifmap_o,
    output logic signed [PSUM_WIDTH-1:0]   psum_o
);

    logic signed [IFMAP_WIDTH-1:0]  ifmap_r;
    logic signed [PSUM_WIDTH-1:0]   psum_r;

    always_ff @(posedge clk or negedge nrst) begin
        if(~nrst) psum_r <= 0;
        else if(pe_en) psum_r <= psum_i + ifmap_i * weight_i;
        else psum_r <= 0;
    end

    always_ff @(posedge clk or negedge nrst) begin
        if(~nrst) ifmap_r <= 0;
        else if(pe_en) ifmap_r <= ifmap_i;
        else ifmap_r <= 0;
    end

    // output assignment
    assign ifmap_o = ifmap_r;
    assign psum_o = psum_r;

endmodule

`default_nettype wire

src/weight_stationary/SA_weight_stationary.sv
`default_nettype none
`timescale 1ns/1ps

// weight stationary 
// for 3-by-3 convolution
module SA_WS_conv #(
    parameter SA_ROW = 3,
    parameter SA_COL = 3,
    parameter DATA_WIDTH = 8,
    parameter PSUM_WIDTH = 19,
    parameter VECTOR_LENGTH = 8
)(
    input wire clk,
    input wire nrst,

    input wire sa_iv, // activate SA array
    input wire [SA_ROW-1:0][DATA_WIDTH-1:0] row_A_i, // layer input

    output logic sa_ov, //when output is ready
    output logic [SA_COL-1:0][PSUM_WIDTH-1:0] psum_o
);

    localparam LATENCY = VECTOR_LENGTH + SA_ROW + SA_COL - 1;
    localparam LATE_WIDTH = $clog2(LATENCY);
    
    logic [LATE_WIDTH-1:0] sa_cnt;
    
    logic [SA_ROW:0][SA_COL-1:0][PSUM_WIDTH-1:0] psum_w;
    logic [SA_ROW-1:0][SA_COL:0][DATA_WIDTH-1:0] ifmap_w;
    logic [SA_ROW-1:0][SA_COL-1:0][DATA_WIDTH-1:0] weight_w;

    always_ff @(posedge clk or negedge nrst) begin
        if(~nrst) sa_cnt <= 0;
        else if(sa_iv) sa_cnt <= sa_cnt + 1;
        else sa_cnt <= 0;
    end

    // output valid assignment
    assign sa_ov = ((sa_cnt>=(SA_ROW+SA_COL-1)) && (sa_cnt<=(VECTOR_LENGTH+SA_ROW-1))) ? 1'b1 : 1'b0;


    // edge assignment: ifmap_i and psum_i
    genvar row, col;
    generate
        for(row=0; row<SA_ROW; row=row+1) begin
            assign ifmap_w[row][0] = row_A_i[row];
        end

        for(col=0; col<SA_COL; col=col+1) begin
            assign psum_w[0][col] = 0;
            assign psum_o[col] = psum_w[SA_ROW][col];
        end
    endgenerate

    // SA array 
    genvar r, c;
    generate 
        for(r=0; r<SA_ROW; r=r+1) begin: R
            for(c=0; c<SA_COL; c=c+1) begin: C
                PE_weight_stationary#(
                    .IFMAP_WIDTH        ( 8 ),
                    .WEIGHT_WIDTH       ( 8 ),
                    .ACCUMULATION_WIDTH ( 4 )
                )u_PE_weight_stationary(
                    .clk       ( clk              ),
                    .nrst      ( nrst             ),
                    .ifmap_i   ( ifmap_w[r][c]    ),
                    .psum_i    ( psum_w[r][c]     ),
                    .weight_i  ( weight_w[r][c]   ),
                    .pe_en     ( sa_iv            ),
                    .ifmap_o   ( ifmap_w[r][c+1]  ),
                    .psum_o    ( psum_w[r+1][c]   ) 
                );

            end
        end
    endgenerate 

    // weight assignment
    weight_kernel_conv0#(
        .KERNEL_WIDTH  ( 3 ),
        .KERNEL_HEIGHT ( 3 ),
        .WEIGHT_WIDTH  ( 8 )
    )u_weight_kernel_conv0(
        .weight_o  ( weight_w  )
    );


endmodule 

`default_nettype wire

sim/tb_ws_conv_bias_reLU.sv
`default_nettype none
`timescale 1ns/1ps

module tb_ws_layer;

    parameter SA_ROW = 3;
    parameter SA_COL = 3;
    parameter DATA_WIDTH = 8;
    parameter PSUM_WIDTH = 19;
    parameter VECTOR_LENGTH = 8;
    parameter LATENCY = VECTOR_LENGTH + SA_ROW + SA_COL - 1;

    logic clk;
    logic nrst;

    logic sa_iv; // activate SA array
    logic [SA_ROW-1:0][DATA_WIDTH-1:0] row_A_i; // layer input

    logic sa_ov; //when output is ready
    logic [SA_COL-1:0][PSUM_WIDTH-1:0] psum_o;
    logic [PSUM_WIDTH-1:0] psum_o0, psum_o1, psum_o2;

    logic biased_ov;
    logic [DATA_WIDTH-1:0] biased_od;

    logic reLU_ov;
    logic [DATA_WIDTH-1:0] reLU_od;

    assign {psum_o2, psum_o1, psum_o0} = psum_o;

    SA_WS_conv#(
        .SA_ROW        ( SA_ROW ),
        .SA_COL        ( SA_COL),
        .DATA_WIDTH    ( DATA_WIDTH ),
        .PSUM_WIDTH    ( PSUM_WIDTH ),
        .VECTOR_LENGTH ( VECTOR_LENGTH )
    )u_SA_WS_conv(
        .clk     ( clk     ),
        .nrst    ( nrst    ),
        .sa_iv   ( sa_iv   ),
        .row_A_i ( row_A_i ),
        .sa_ov   ( sa_ov   ),
        .psum_o  ( psum_o  )
    );

    bias_adder#(
        .BIAS            ( 8'd10 ),
        .PSUM_WIDTH      ( PSUM_WIDTH ),
        .DATA_WIDTH      ( DATA_WIDTH ),
        .SA_COL          ( SA_COL )
    )u_bias_adder(
        .clk             ( clk             ),
        .nrst            ( nrst            ),
        .bias_adder_iv   ( sa_ov   ),
        .psum_i          ( psum_o          ),
        .biased_ov ( biased_ov ),
        .biased_od  ( biased_od  )
    );

    reLU#(
        .DATA_WIDTH    ( DATA_WIDTH )
    )u_reLU(
        .clk           ( clk           ),
        .nrst          ( nrst          ),
        .reLU_iv       ( biased_ov       ),
        .neuron_i      ( biased_od      ),
        .reLU_ov    ( reLU_ov ),
        .reLU_od    ( reLU_od  )
    );


    always begin
        #5 clk = ~clk;
    end

    initial begin
        $display("Starting Sim"); //print nice message
        $dumpfile("sim/vcd/layer_weight_stationary.vcd"); //file to store value change dump (vcd)
        $dumpvars(0,tb_ws_layer); //store everything at the current level and below
        $display("Testing assorted values");
        
        //initalize
        clk = 1;
        nrst = 1'b0;
        sa_iv = 1'b0;
        for(int i=0; i<SA_ROW; i=i+1) begin
            row_A_i[i] = 0;
        end
        #1; nrst = 1'b1;
        #20;

        // ready to send data
        #10 sa_iv = 1'b1;
            row_A_i = {8'sd0, 8'sd0, 8'sd3}; // 2nd-byte, 1st-byte, 0th-byte
        #10 row_A_i = {8'sd0, 8'sd2, 8'sd3};
        #10 row_A_i = {8'sd1, 8'sd2, 8'sd3};
        #10 row_A_i = {8'sd1, 8'sd2, 8'sd3};
        #10 row_A_i = {8'sd1, 8'sd2, 8'sd3};
        #10 row_A_i = {8'sd1, 8'sd2, 8'sd3};
        #10 row_A_i = {8'sd1, 8'sd2, 8'sd3};
        #10 row_A_i = {8'sd1, 8'sd2, 8'sd3};
        #10 row_A_i = {8'sd1, 8'sd2, 8'sd0};
        #10 row_A_i = {8'sd1, 8'sd0, 8'sd0};
        #10 sa_iv = 1'b0;
            row_A_i = {8'sd0, 8'sd0, 8'sd0};
        
        #100;
        
        $display("Finishing Sim"); //print nice message
        $finish;
    end
endmodule
`default_nettype wire

sim/vcd/layer_weight_stationary.vcd
$date
	Tue Nov 08 17:37:38 2022
$end
$version
	Icarus Verilog
$end
$timescale
	1ps
$end
$scope module tb_ws_layer $end
$var wire 1 ! sa_ov $end
$var wire 1 " reLU_ov $end
$var wire 8 # reLU_od [7:0] $end
$var wire 19 $ psum_o2 [18:0] $end
$var wire 19 % psum_o1 [18:0] $end
$var wire 19 & psum_o0 [18:0] $end
$var wire 57 ' psum_o [56:0] $end
$var wire 1 ( biased_ov $end
$var wire 8 ) biased_od [7:0] $end
$var parameter 32 * DATA_WIDTH $end
$var parameter 35 + LATENCY $end
$var parameter 32 , PSUM_WIDTH $end
$var parameter 32 - SA_COL $end
$var parameter 32 . SA_ROW $end
$var parameter 32 / VECTOR_LENGTH $end
$var reg 1 0 clk $end
$var reg 1 1 nrst $end
$var reg 24 2 row_A_i [23:0] $end
$var reg 1 3 sa_iv $end
$scope module u_SA_WS_conv $end
$var wire 1 0 clk $end
$var wire 1 1 nrst $end
$var wire 24 4 row_A_i [23:0] $end
$var wire 1 3 sa_iv $end
$var wire 72 5 weight_w [71:0] $end
$var wire 1 ! sa_ov $end
$var wire 228 6 psum_w [227:0] $end
$var wire 57 7 psum_o [56:0] $end
$var wire 96 8 ifmap_w [95:0] $end
$var parameter 32 9 DATA_WIDTH $end
$var parameter 35 : LATENCY $end
$var parameter 32 ; LATE_WIDTH $end
$var parameter 32 < PSUM_WIDTH $end
$var parameter 32 = SA_COL $end
$var parameter 32 > SA_ROW $end
$var parameter 32 ? VECTOR_LENGTH $end
$var reg 4 @ sa_cnt [3:0] $end
$scope begin R[0] $end
$var parameter 2 A r $end
$scope begin C[0] $end
$var parameter 2 B c $end
$scope module u_PE_weight_stationary $end
$var wire 1 0 clk $end
$var wire 8 C ifmap_i [7:0] $end
$var wire 1 1 nrst $end
$var wire 1 3 pe_en $end
$var wire 20 D psum_i [19:0] $end
$var wire 8 E weight_i [7:0] $end
$var wire 20 F psum_o [19:0] $end
$var wire 8 G ifmap_o [7:0] $end
$var parameter 32 H ACCUMULATION_WIDTH $end
$var parameter 32 I IFMAP_WIDTH $end
$var parameter 34 J PSUM_WIDTH $end
$var parameter 32 K WEIGHT_WIDTH $end
$var reg 8 L ifmap_r [7:0] $end
$var reg 20 M psum_r [19:0] $end
$upscope $end
$upscope $end
$scope begin C[1] $end
$var parameter 2 N c $end
$scope module u_PE_weight_stationary $end
$var wire 1 0 clk $end
$var wire 8 O ifmap_i [7:0] $end
$var wire 1 1 nrst $end
$var wire 1 3 pe_en $end
$var wire 20 P psum_i [19:0] $end
$var wire 8 Q weight_i [7:0] $end
$var wire 20 R psum_o [19:0] $end
$var wire 8 S ifmap_o [7:0] $end
$var parameter 32 T ACCUMULATION_WIDTH $end
$var parameter 32 U IFMAP_WIDTH $end
$var parameter 34 V PSUM_WIDTH $end
$var parameter 32 W WEIGHT_WIDTH $end
$var reg 8 X ifmap_r [7:0] $end
$var reg 20 Y psum_r [19:0] $end
$upscope $end
$upscope $end
$scope begin C[2] $end
$var parameter 3 Z c $end
$scope module u_PE_weight_stationary $end
$var wire 1 0 clk $end
$var wire 8 [ ifmap_i [7:0] $end
$var wire 1 1 nrst $end
$var wire 1 3 pe_en $end
$var wire 20 \ psum_i [19:0] $end
$var wire 8 ] weight_i [7:0] $end
$var wire 20 ^ psum_o [19:0] $end
$var wire 8 _ ifmap_o [7:0] $end
$var parameter 32 ` ACCUMULATION_WIDTH $end
$var parameter 32 a IFMAP_WIDTH $end
$var parameter 34 b PSUM_WIDTH $end
$var parameter 32 c WEIGHT_WIDTH $end
$var reg 8 d ifmap_r [7:0] $end
$var reg 20 e psum_r [19:0] $end
$upscope $end
$upscope $end
$upscope $end
$scope begin R[1] $end
$var parameter 2 f r $end
$scope begin C[0] $end
$var parameter 2 g c $end
$scope module u_PE_weight_stationary $end
$var wire 1 0 clk $end
$var wire 8 h ifmap_i [7:0] $end
$var wire 1 1 nrst $end
$var wire 1 3 pe_en $end
$var wire 20 i psum_i [19:0] $end
$var wire 8 j weight_i [7:0] $end
$var wire 20 k psum_o [19:0] $end
$var wire 8 l ifmap_o [7:0] $end
$var parameter 32 m ACCUMULATION_WIDTH $end
$var parameter 32 n IFMAP_WIDTH $end
$var parameter 34 o PSUM_WIDTH $end
$var parameter 32 p WEIGHT_WIDTH $end
$var reg 8 q ifmap_r [7:0] $end
$var reg 20 r psum_r [19:0] $end
$upscope $end
$upscope $end
$scope begin C[1] $end
$var parameter 2 s c $end
$scope module u_PE_weight_stationary $end
$var wire 1 0 clk $end
$var wire 8 t ifmap_i [7:0] $end
$var wire 1 1 nrst $end
$var wire 1 3 pe_en $end
$var wire 20 u psum_i [19:0] $end
$var wire 8 v weight_i [7:0] $end
$var wire 20 w psum_o [19:0] $end
$var wire 8 x ifmap_o [7:0] $end
$var parameter 32 y ACCUMULATION_WIDTH $end
$var parameter 32 z IFMAP_WIDTH $end
$var parameter 34 { PSUM_WIDTH $end
$var parameter 32 | WEIGHT_WIDTH $end
$var reg 8 } ifmap_r [7:0] $end
$var reg 20 ~ psum_r [19:0] $end
$upscope $end
$upscope $end
$scope begin C[2] $end
$var parameter 3 !" c $end
$scope module u_PE_weight_stationary $end
$var wire 1 0 clk $end
$var wire 8 "" ifmap_i [7:0] $end
$var wire 1 1 nrst $end
$var wire 1 3 pe_en $end
$var wire 20 #" psum_i [19:0] $end
$var wire 8 $" weight_i [7:0] $end
$var wire 20 %" psum_o [19:0] $end
$var wire 8 &" ifmap_o [7:0] $end
$var parameter 32 '" ACCUMULATION_WIDTH $end
$var parameter 32 (" IFMAP_WIDTH $end
$var parameter 34 )" PSUM_WIDTH $end
$var parameter 32 *" WEIGHT_WIDTH $end
$var reg 8 +" ifmap_r [7:0] $end
$var reg 20 ," psum_r [19:0] $end
$upscope $end
$upscope $end
$upscope $end
$scope begin R[2] $end
$var parameter 3 -" r $end
$scope begin C[0] $end
$var parameter 2 ." c $end
$scope module u_PE_weight_stationary $end
$var wire 1 0 clk $end
$var wire 8 /" ifmap_i [7:0] $end
$var wire 1 1 nrst $end
$var wire 1 3 pe_en $end
$var wire 20 0" psum_i [19:0] $end
$var wire 8 1" weight_i [7:0] $end
$var wire 20 2" psum_o [19:0] $end
$var wire 8 3" ifmap_o [7:0] $end
$var parameter 32 4" ACCUMULATION_WIDTH $end
$var parameter 32 5" IFMAP_WIDTH $end
$var parameter 34 6" PSUM_WIDTH $end
$var parameter 32 7" WEIGHT_WIDTH $end
$var reg 8 8" ifmap_r [7:0] $end
$var reg 20 9" psum_r [19:0] $end
$upscope $end
$upscope $end
$scope begin C[1] $end
$var parameter 2 :" c $end
$scope module u_PE_weight_stationary $end
$var wire 1 0 clk $end
$var wire 8 ;" ifmap_i [7:0] $end
$var wire 1 1 nrst $end
$var wire 1 3 pe_en $end
$var wire 20 <" psum_i [19:0] $end
$var wire 8 =" weight_i [7:0] $end
$var wire 20 >" psum_o [19:0] $end
$var wire 8 ?" ifmap_o [7:0] $end
$var parameter 32 @" ACCUMULATION_WIDTH $end
$var parameter 32 A" IFMAP_WIDTH $end
$var parameter 34 B" PSUM_WIDTH $end
$var parameter 32 C" WEIGHT_WIDTH $end
$var reg 8 D" ifmap_r [7:0] $end
$var reg 20 E" psum_r [19:0] $end
$upscope $end
$upscope $end
$scope begin C[2] $end
$var parameter 3 F" c $end
$scope module u_PE_weight_stationary $end
$var wire 1 0 clk $end
$var wire 8 G" ifmap_i [7:0] $end
$var wire 1 1 nrst $end
$var wire 1 3 pe_en $end
$var wire 20 H" psum_i [19:0] $end
$var wire 8 I" weight_i [7:0] $end
$var wire 20 J" psum_o [19:0] $end
$var wire 8 K" ifmap_o [7:0] $end
$var parameter 32 L" ACCUMULATION_WIDTH $end
$var parameter 32 M" IFMAP_WIDTH $end
$var parameter 34 N" PSUM_WIDTH $end
$var parameter 32 O" WEIGHT_WIDTH $end
$var reg 8 P" ifmap_r [7:0] $end
$var reg 20 Q" psum_r [19:0] $end
$upscope $end
$upscope $end
$upscope $end
$scope begin genblk1[0] $end
$var parameter 2 R" row $end
$upscope $end
$scope begin genblk1[1] $end
$var parameter 2 S" row $end
$upscope $end
$scope begin genblk1[2] $end
$var parameter 3 T" row $end
$upscope $end
$scope begin genblk2[0] $end
$var parameter 2 U" col $end
$upscope $end
$scope begin genblk2[1] $end
$var parameter 2 V" col $end
$upscope $end
$scope begin genblk2[2] $end
$var parameter 3 W" col $end
$upscope $end
$scope module u_weight_kernel_conv0 $end
$var wire 72 X" weight_o [71:0] $end
$var parameter 32 Y" KERNEL_HEIGHT $end
$var parameter 32 Z" KERNEL_WIDTH $end
$var parameter 32 [" WEIGHT_WIDTH $end
$upscope $end
$upscope $end
$scope module u_bias_adder $end
$var wire 1 ! bias_adder_iv $end
$var wire 1 0 clk $end
$var wire 1 1 nrst $end
$var wire 57 \" psum_i [56:0] $end
$var wire 1 ]" psum_sv $end
$var wire 19 ^" psum_sd_shifted [18:0] $end
$var wire 19 _" psum_sd [18:0] $end
$var parameter 8 `" BIAS $end
$var parameter 32 a" DATA_WIDTH $end
$var parameter 32 b" PSUM_WIDTH $end
$var parameter 32 c" SA_COL $end
$var reg 8 d" biased_od [7:0] $end
$var reg 1 ( biased_ov $end
$scope module u_multiport_adder $end
$var wire 1 0 clk $end
$var wire 1 1 nrst $end
$var wire 57 e" port_id [56:0] $end
$var wire 1 ! port_iv $end
$var wire 19 f" sum_r1 [18:0] $end
$var wire 19 g" sum_r0 [18:0] $end
$var wire 1 ]" sum_ov $end
$var wire 19 h" sum_od [18:0] $end
$var parameter 32 i" WIDTH $end
$var reg 19 j" port_id_pipe [18:0] $end
$var reg 2 k" port_iv_pipe [1:0] $end
$var reg 38 l" sum_r [37:0] $end
$upscope $end
$upscope $end
$scope module u_reLU $end
$var wire 1 0 clk $end
$var wire 8 m" neuron_i [7:0] $end
$var wire 1 1 nrst $end
$var wire 1 ( reLU_iv $end
$var parameter 32 n" DATA_WIDTH $end
$var reg 8 o" reLU_od [7:0] $end
$var reg 1 " reLU_ov $end
$upscope $end
$scope begin $ivl_for_loop0 $end
$var integer 32 p" i [31:0] $end
$upscope $end
$upscope $end
$enddefinitions $end
$comment Show the parameter values. $end
$dumpall
b1000 n"
b10011 i"
b11 c"
b10011 b"
b1000 a"
b1010 `"
b1000 ["
b11 Z"
b11 Y"
b10 W"
b1 V"
b0 U"
b10 T"
b1 S"
b0 R"
b1000 O"
b10100 N"
b1000 M"
b100 L"
b10 F"
b1000 C"
b10100 B"
b1000 A"
b100 @"
b1 :"
b1000 7"
b10100 6"
b1000 5"
b100 4"
b0 ."
b10 -"
b1000 *"
b10100 )"
b1000 ("
b100 '"
b10 !"
b1000 |
b10100 {
b1000 z
b100 y
b1 s
b1000 p
b10100 o
b1000 n
b100 m
b0 g
b1 f
b1000 c
b10100 b
b1000 a
b100 `
b10 Z
b1000 W
b10100 V
b1000 U
b100 T
b1 N
b1000 K
b10100 J
b1000 I
b100 H
b0 B
b0 A
b1000 ?
b11 >
b11 =
b10011 <
b100 ;
b1101 :
b1000 9
b1000 /
b11 .
b11 -
b10011 ,
b1101 +
b1000 *
$end
#0
$dumpvars
b11 p"
b0 o"
b0 m"
b0 l"
b0 k"
b0 j"
b0 h"
b0 g"
b0 f"
b0 e"
b0 d"
b0 _"
b0 ^"
0]"
b0 \"
b1000000010000000100000001000000010000000100000001000000010000000100000 X"
b0 Q"
b0 P"
b0 K"
b0 J"
b100000 I"
b0 H"
b0 G"
b0 E"
b0 D"
b0 ?"
b0 >"
b100000 ="
b0 <"
b0 ;"
b0 9"
b0 8"
b0 3"
b0 2"
b100000 1"
b0 0"
b0 /"
b0 ,"
b0 +"
b0 &"
b0 %"
b100000 $"
b0 #"
b0 ""
b0 ~
b0 }
b0 x
b0 w
b100000 v
b0 u
b0 t
b0 r
b0 q
b0 l
b0 k
b100000 j
b0 i
b0 h
b0 e
b0 d
b0 _
b0 ^
b100000 ]
b0 \
b0 [
b0 Y
b0 X
b0 S
b0 R
b100000 Q
b0 P
b0 O
b0 M
b0 L
b0 G
b0 F
b100000 E
b0 D
b0 C
b0 @
b0 8
b0 7
b0 6
b1000000010000000100000001000000010000000100000001000000010000000100000 5
b0 4
03
b0 2
01
10
b0 )
0(
b0 '
b0 &
b0 %
b0 $
b0 #
0"
0!
$end
#1000
11
#5000
00
#10000
10
#15000
00
#20000
10
#25000
00
#30000
10
#31000
b11 C
b11 8
b11 2
b11 4
13
#35000
00
#40000
b1100000 i
b1100000000000000000000000000000000000000000000000000000000000000 6
b11 O
b1100000 F
b1100000 M
b1100000011 8
b11 G
b11 L
b1 @
10
#41000
b10 h
b1000000000000000000000001100000011 8
b1000000011 2
b1000000011 4
#45000
00
#50000
b10100000 0"
b1100000 u
b10 t
b11 [
b10100000000000000000000000000000000000011000000000000000001100000000000000000000000000000000000000000000000000000000000000 6
b10 @
b10 l
b10 q
b10100000 k
b10100000 r
b100000001000000000000000110000001100000011 8
b11 S
b11 X
b1100000 R
b1100000 Y
10
#51000
b1 /"
b10000000000000000000000100000001000000000000000110000001100000011 8
b10000001000000011 2
b10000001000000011 4
#55000
00
#60000
b11000000 &
b1100000 #"
b10100000 <"
b11000000 '
b11000000 7
b11000000 \"
b11000000 e"
b10 ""
b11000000000000000000000000000000000000101000000000000000010100000000000000000110000000000000000011000000000000000001100000000000000000000000000000000000000000000000000000000000000 6
b1 ;"
b1100000 ^
b1100000 e
b11 _
b11 d
b10100000 w
b10100000 ~
b10 x
b10 }
b11000000 2"
b11000000 9"
b1000000010000000000000010000000100000001000000011000000110000001100000011 8
b1 3"
b1 8"
b11 @
10
#65000
00
#70000
b11000000 %
b110000000000000000011000000 '
b110000000000000000011000000 7
b110000000000000000011000000 \"
b110000000000000000011000000 e"
b10100000 H"
b1 G"
b110000000000000000011000000000000000001010000000000000000101000000000000000010100000000000000000110000000000000000011000000000000000001100000000000000000000000000000000000000000000000000000000000000 6
b100 @
b1 ?"
b1 D"
b11000000 >"
b11000000 E"
b100000001000000010000001000000010000000100000001000000011000000110000001100000011 8
b10 &"
b10 +"
b10100000 %"
b10100000 ,"
10
#75000
00
#80000
b11000000 $
b1100000000000000000110000000000000000011000000 '
b1100000000000000000110000000000000000011000000 7
b1100000000000000000110000000000000000011000000 \"
b1100000000000000000110000000000000000011000000 e"
1!
b1100000000000000000110000000000000000011000000000000000001010000000000000000101000000000000000010100000000000000000110000000000000000011000000000000000001100000000000000000000000000000000000000000000000000000000000000 6
b11000000 J"
b11000000 Q"
b10000000100000001000000010000001000000010000000100000001000000011000000110000001100000011 8
b1 K"
b1 P"
b101 @
10
#85000
00
#90000
b110000000 g"
b110000000 l"
b1 k"
b11000000 j"
b110 @
10
#95000
00
#100000
b100 ^"
1]"
b1001000000 _"
b1001000000 h"
b1001000000 f"
b111 @
b11 k"
b10010000000000000000110000000 l"
10
#105000
00
#110000
b1110 )
b1110 d"
b1110 m"
1(
b1000 @
10
#111000
b0 C
b10000000100000001000000010000001000000010000000100000001000000011000000110000001100000000 8
b10000001000000000 2
b10000001000000000 4
#115000
00
#120000
b0 i
b1100000000000000000110000000000000000011000000000000000001010000000000000000101000000000000000010100000000000000000110000000000000000011000000000000000000000000000000000000000000000000000000000000000000000000000000000 6
b0 O
b0 F
b0 M
b10000000100000001000000010000001000000010000000100000001000000011000000110000000000000000 8
b0 G
b0 L
b1001 @
b1110 #
b1110 o"
1"
10
#121000
b0 h
b10000000100000001000000010000001000000010000000100000000000000011000000110000000000000000 8
b10000000000000000 2
b10000000000000000 4
#125000
00
#130000
b0 0"
b0 u
b0 t
b0 [
b1100000000000000000110000000000000000011000000000000000001010000000000000000101000000000000000000000000000000000000110000000000000000000000000000000000000000000000000000000000000000000000000000000000000000000000000000 6
b1010 @
b0 l
b0 q
b0 k
b0 r
b10000000100000001000000010000001000000010000000000000000000000011000000000000000000000000 8
b0 S
b0 X
b0 R
b0 Y
10
#131000
b0 /"
b10000000100000001000000000000001000000010000000000000000000000011000000000000000000000000 8
b0 2
b0 4
03
#135000
00
#140000
b0 &
b0 %
b0 $
b0 #"
b0 <"
b0 H"
b0 '
b0 7
b0 \"
b0 e"
0!
b0 ""
b0 ;"
b0 G"
b0 6
b0 ^
b0 e
b0 _
b0 d
b0 w
b0 ~
b0 x
b0 }
b0 %"
b0 ,"
b0 &"
b0 +"
b0 2"
b0 9"
b0 3"
b0 8"
b0 >"
b0 E"
b0 ?"
b0 D"
b0 J"
b0 Q"
b0 8
b0 K"
b0 P"
b0 @
10
#145000
00
#150000
b0 g"
b10010000000000000000000000000 l"
b10 k"
b0 j"
10
#155000
00
#160000
b0 ^"
0]"
b0 _"
b0 h"
b0 f"
b0 k"
b0 l"
10
#165000
00
#170000
b0 )
b0 d"
b0 m"
0(
10
#175000
00
#180000
b0 #
b0 o"
0"
10
