src/weight_stationary/weight_kernel_conv0.sv
`default_nettype none
`timescale 1ns/1ps

// A:m*l, B:l*n, AB:m*n
module weight_kernel_conv0 #(
    parameter KERNEL_WIDTH = 3,
    parameter KERNEL_HEIGHT = 3,
    parameter WEIGHT_WIDTH = 8
)(
    output logic signed [KERNEL_HEIGHT-1:0][KERNEL_WIDTH-1:0][WEIGHT_WIDTH-1:0] weight_o
);

    /*
    00 01 02
    10 11 12
    20 21 22
    */
    assign weight_o = {8'sb00100000, 8'sb00100000, 8'sb00100000,
                       8'sb00100000, 8'sb00100000, 8'sb00100000,
                       8'sb00100000, 8'sb00100000, 8'sb00100000 }; // 22, 21, 20, 12, 11, 10, 02, 01, 00

endmodule 

`default_nettype wire

src/weight_stationary/PE_weight_stationary.sv
`default_nettype none
`timescale 1ns/1ps

module PE_weight_stationary #(
    parameter IFMAP_WIDTH = 8,
    parameter WEIGHT_WIDTH = 8,
    parameter ACCUMULATION_WIDTH = 3, // since 8x8*8x8, log2(8)=3 to avoid overflow
    parameter PSUM_WIDTH = IFMAP_WIDTH + WEIGHT_WIDTH + ACCUMULATION_WIDTH
)(
    input wire clk,
    input wire nrst,

    input wire signed [IFMAP_WIDTH-1:0]  ifmap_i,
    input wire signed [PSUM_WIDTH-1:0]   psum_i,
    input wire signed [WEIGHT_WIDTH-1:0] weight_i,
    input wire pe_en,

    output logic signed [IFMAP_WIDTH-1:0]  ifmap_o,
    output logic signed [PSUM_WIDTH-1:0]   psum_o
);

    logic signed [IFMAP_WIDTH-1:0]  ifmap_r;
    logic signed [PSUM_WIDTH-1:0]   psum_r;

    always_ff @(posedge clk or negedge nrst) begin
        if(~nrst) psum_r <= 0;
        else if(pe_en) psum_r <= psum_i + ifmap_i * weight_i;
        else psum_r <= 0;
    end

    always_ff @(posedge clk or negedge nrst) begin
        if(~nrst) ifmap_r <= 0;
        else if(pe_en) ifmap_r <= ifmap_i;
        else ifmap_r <= 0;
    end

    // output assignment
    assign ifmap_o = ifmap_r;
    assign psum_o = psum_r;

endmodule

`default_nettype wire

src/weight_stationary/SA_weight_stationary.sv
`default_nettype none
`timescale 1ns/1ps

// weight stationary 
// for 3-by-3 convolution
module SA_WS_conv #(
    parameter SA_ROW = 3,
    parameter SA_COL = 3,
    parameter DATA_WIDTH = 8,
    parameter PSUM_WIDTH = 19,
    parameter VECTOR_LENGTH = 8
)(
    input wire clk,
    input wire nrst,

    input wire sa_iv, // activate SA array
    input wire [SA_ROW-1:0][DATA_WIDTH-1:0] row_A_i, // layer input

    output logic sa_ov, //when output is ready
    output logic [SA_COL-1:0][PSUM_WIDTH-1:0] psum_o
);

    localparam LATENCY = VECTOR_LENGTH + SA_ROW + SA_COL - 1;
    localparam LATE_WIDTH = $clog2(LATENCY);
    
    logic [LATE_WIDTH-1:0] sa_cnt;
    
    logic [SA_ROW:0][SA_COL-1:0][PSUM_WIDTH-1:0] psum_w;
    logic [SA_ROW-1:0][SA_COL:0][DATA_WIDTH-1:0] ifmap_w;
    logic [SA_ROW-1:0][SA_COL-1:0][DATA_WIDTH-1:0] weight_w;

    always_ff @(posedge clk or negedge nrst) begin
        if(~nrst) sa_cnt <= 0;
        else if(sa_iv) sa_cnt <= sa_cnt + 1;
        else sa_cnt <= 0;
    end

    // output valid assignment
    assign sa_ov = ((sa_cnt>=(SA_ROW+SA_COL-1)) && (sa_cnt<=(VECTOR_LENGTH+SA_ROW-1))) ? 1'b1 : 1'b0;


    // edge assignment: ifmap_i and psum_i
    genvar row, col;
    generate
        for(row=0; row<SA_ROW; row=row+1) begin
            assign ifmap_w[row][0] = row_A_i[row];
        end

        for(col=0; col<SA_COL; col=col+1) begin
            assign psum_w[0][col] = 0;
            assign psum_o[col] = psum_w[SA_ROW][col];
        end
    endgenerate

    // SA array 
    genvar r, c;
    generate 
        for(r=0; r<SA_ROW; r=r+1) begin: R
            for(c=0; c<SA_COL; c=c+1) begin: C
                PE_weight_stationary#(
                    .IFMAP_WIDTH        ( 8 ),
                    .WEIGHT_WIDTH       ( 8 ),
                    .ACCUMULATION_WIDTH ( 4 )
                )u_PE_weight_stationary(
                    .clk       ( clk              ),
                    .nrst      ( nrst             ),
                    .ifmap_i   ( ifmap_w[r][c]    ),
                    .psum_i    ( psum_w[r][c]     ),
                    .weight_i  ( weight_w[r][c]   ),
                    .pe_en     ( sa_iv            ),
                    .ifmap_o   ( ifmap_w[r][c+1]  ),
                    .psum_o    ( psum_w[r+1][c]   ) 
                );

            end
        end
    endgenerate 

    // weight assignment
    weight_kernel_conv0#(
        .KERNEL_WIDTH  ( 3 ),
        .KERNEL_HEIGHT ( 3 ),
        .WEIGHT_WIDTH  ( 8 )
    )u_weight_kernel_conv0(
        .weight_o  ( weight_w  )
    );


endmodule 

`default_nettype wire

sim/tb_ws_conv.sv
`default_nettype none
`timescale 1ns/1ps

module tb_ws_conv;

    parameter SA_ROW = 3;
    parameter SA_COL = 3;
    parameter DATA_WIDTH = 8;
    parameter PSUM_WIDTH = 19;
    parameter VECTOR_LENGTH = 8;
    parameter LATENCY = VECTOR_LENGTH + SA_ROW + SA_COL - 1;

    logic clk;
    logic nrst;

    logic sa_iv; // activate SA array
    logic [SA_ROW-1:0][DATA_WIDTH-1:0] row_A_i; // layer input

    logic sa_ov; //when output is ready
    logic [SA_COL-1:0][PSUM_WIDTH-1:0] psum_o;
    logic [PSUM_WIDTH-1:0] psum_o0, psum_o1, psum_o2;

    assign {psum_o2, psum_o1, psum_o0} = psum_o;

    SA_WS_conv#(
        .SA_ROW        ( 3 ),
        .SA_COL        ( 3 ),
        .DATA_WIDTH    ( 8 ),
        .PSUM_WIDTH    ( 19 ),
        .VECTOR_LENGTH ( 8 )
    )u_SA_WS_conv(
        .clk     ( clk     ),
        .nrst    ( nrst    ),
        .sa_iv   ( sa_iv   ),
        .row_A_i ( row_A_i ),
        .sa_ov   ( sa_ov   ),
        .psum_o  ( psum_o  )
    );


    initial begin
        clk = 1'd1;
        forever 
            #5 clk = ~clk;
    end

    initial begin
        $display("Starting Sim"); //print nice message
        $dumpfile("sim/vcd/sa_weight_stationary.vcd"); //file to store value change dump (vcd)
        $dumpvars(0,tb_ws_conv); //store everything at the current level and below
        $display("Testing assorted values");
        
        //initalize
        nrst = 1'b0;
        sa_iv = 1'b0;
        for(int i=0; i<SA_ROW; i=i+1) begin
            row_A_i[i] = 0;
        end
        #1; nrst = 1'b1;
        #20

        // ready to send data
        #10 sa_iv = 1'b1;
            row_A_i = {8'sd0, 8'sd0, 8'sd3}; // 2nd-byte, 1st-byte, 0th-byte
        #10 row_A_i = {8'sd0, 8'sd2, 8'sd3};
        #10 row_A_i = {8'sd1, 8'sd2, 8'sd3};
        #10 row_A_i = {8'sd1, 8'sd2, 8'sd3};
        #10 row_A_i = {8'sd1, 8'sd2, 8'sd3};
        #10 row_A_i = {8'sd1, 8'sd2, 8'sd3};
        #10 row_A_i = {8'sd1, 8'sd2, 8'sd3};
        #10 row_A_i = {8'sd1, 8'sd2, 8'sd3};
        #10 row_A_i = {8'sd1, 8'sd2, 8'sd0};
        #10 row_A_i = {8'sd1, 8'sd0, 8'sd0};
        #10 sa_iv = 1'b0;
            row_A_i = {8'sd0, 8'sd0, 8'sd0};
        
        #100;
        
        $display("Finishing Sim"); //print nice message
        $finish;
    end
endmodule
`default_nettype wire

sim/vcd/sa_weight_stationary.vcd
$date
	Tue Nov 08 16:14:31 2022
$end
$version
	Icarus Verilog
$end
$timescale
	1ps
$end
$scope module tb_ws_conv $end
$var wire 1 ! sa_ov $end
$var wire 19 " psum_o2 [18:0] $end
$var wire 19 # psum_o1 [18:0] $end
$var wire 19 $ psum_o0 [18:0] $end
$var wire 57 % psum_o [56:0] $end
$var parameter 32 & DATA_WIDTH $end
$var parameter 35 ' LATENCY $end
$var parameter 32 ( PSUM_WIDTH $end
$var parameter 32 ) SA_COL $end
$var parameter 32 * SA_ROW $end
$var parameter 32 + VECTOR_LENGTH $end
$var reg 1 , clk $end
$var reg 1 - nrst $end
$var reg 24 . row_A_i [23:0] $end
$var reg 1 / sa_iv $end
$scope module u_SA_WS_conv $end
$var wire 1 , clk $end
$var wire 1 - nrst $end
$var wire 24 0 row_A_i [23:0] $end
$var wire 1 / sa_iv $end
$var wire 72 1 weight_w [71:0] $end
$var wire 1 ! sa_ov $end
$var wire 228 2 psum_w [227:0] $end
$var wire 57 3 psum_o [56:0] $end
$var wire 96 4 ifmap_w [95:0] $end
$var parameter 32 5 DATA_WIDTH $end
$var parameter 35 6 LATENCY $end
$var parameter 32 7 LATE_WIDTH $end
$var parameter 32 8 PSUM_WIDTH $end
$var parameter 32 9 SA_COL $end
$var parameter 32 : SA_ROW $end
$var parameter 32 ; VECTOR_LENGTH $end
$var reg 4 < sa_cnt [3:0] $end
$scope begin R[0] $end
$var parameter 2 = r $end
$scope begin C[0] $end
$var parameter 2 > c $end
$scope module u_PE_weight_stationary $end
$var wire 1 , clk $end
$var wire 8 ? ifmap_i [7:0] $end
$var wire 1 - nrst $end
$var wire 1 / pe_en $end
$var wire 20 @ psum_i [19:0] $end
$var wire 8 A weight_i [7:0] $end
$var wire 20 B psum_o [19:0] $end
$var wire 8 C ifmap_o [7:0] $end
$var parameter 32 D ACCUMULATION_WIDTH $end
$var parameter 32 E IFMAP_WIDTH $end
$var parameter 34 F PSUM_WIDTH $end
$var parameter 32 G WEIGHT_WIDTH $end
$var reg 8 H ifmap_r [7:0] $end
$var reg 20 I psum_r [19:0] $end
$upscope $end
$upscope $end
$scope begin C[1] $end
$var parameter 2 J c $end
$scope module u_PE_weight_stationary $end
$var wire 1 , clk $end
$var wire 8 K ifmap_i [7:0] $end
$var wire 1 - nrst $end
$var wire 1 / pe_en $end
$var wire 20 L psum_i [19:0] $end
$var wire 8 M weight_i [7:0] $end
$var wire 20 N psum_o [19:0] $end
$var wire 8 O ifmap_o [7:0] $end
$var parameter 32 P ACCUMULATION_WIDTH $end
$var parameter 32 Q IFMAP_WIDTH $end
$var parameter 34 R PSUM_WIDTH $end
$var parameter 32 S WEIGHT_WIDTH $end
$var reg 8 T ifmap_r [7:0] $end
$var reg 20 U psum_r [19:0] $end
$upscope $end
$upscope $end
$scope begin C[2] $end
$var parameter 3 V c $end
$scope module u_PE_weight_stationary $end
$var wire 1 , clk $end
$var wire 8 W ifmap_i [7:0] $end
$var wire 1 - nrst $end
$var wire 1 / pe_en $end
$var wire 20 X psum_i [19:0] $end
$var wire 8 Y weight_i [7:0] $end
$var wire 20 Z psum_o [19:0] $end
$var wire 8 [ ifmap_o [7:0] $end
$var parameter 32 \ ACCUMULATION_WIDTH $end
$var parameter 32 ] IFMAP_WIDTH $end
$var parameter 34 ^ PSUM_WIDTH $end
$var parameter 32 _ WEIGHT_WIDTH $end
$var reg 8 ` ifmap_r [7:0] $end
$var reg 20 a psum_r [19:0] $end
$upscope $end
$upscope $end
$upscope $end
$scope begin R[1] $end
$var parameter 2 b r $end
$scope begin C[0] $end
$var parameter 2 c c $end
$scope module u_PE_weight_stationary $end
$var wire 1 , clk $end
$var wire 8 d ifmap_i [7:0] $end
$var wire 1 - nrst $end
$var wire 1 / pe_en $end
$var wire 20 e psum_i [19:0] $end
$var wire 8 f weight_i [7:0] $end
$var wire 20 g psum_o [19:0] $end
$var wire 8 h ifmap_o [7:0] $end
$var parameter 32 i ACCUMULATION_WIDTH $end
$var parameter 32 j IFMAP_WIDTH $end
$var parameter 34 k PSUM_WIDTH $end
$var parameter 32 l WEIGHT_WIDTH $end
$var reg 8 m ifmap_r [7:0] $end
$var reg 20 n psum_r [19:0] $end
$upscope $end
$upscope $end
$scope begin C[1] $end
$var parameter 2 o c $end
$scope module u_PE_weight_stationary $end
$var wire 1 , clk $end
$var wire 8 p ifmap_i [7:0] $end
$var wire 1 - nrst $end
$var wire 1 / pe_en $end
$var wire 20 q psum_i [19:0] $end
$var wire 8 r weight_i [7:0] $end
$var wire 20 s psum_o [19:0] $end
$var wire 8 t ifmap_o [7:0] $end
$var parameter 32 u ACCUMULATION_WIDTH $end
$var parameter 32 v IFMAP_WIDTH $end
$var parameter 34 w PSUM_WIDTH $end
$var parameter 32 x WEIGHT_WIDTH $end
$var reg 8 y ifmap_r [7:0] $end
$var reg 20 z psum_r [19:0] $end
$upscope $end
$upscope $end
$scope begin C[2] $end
$var parameter 3 { c $end
$scope module u_PE_weight_stationary $end
$var wire 1 , clk $end
$var wire 8 | ifmap_i [7:0] $end
$var wire 1 - nrst $end
$var wire 1 / pe_en $end
$var wire 20 } psum_i [19:0] $end
$var wire 8 ~ weight_i [7:0] $end
$var wire 20 !" psum_o [19:0] $end
$var wire 8 "" ifmap_o [7:0] $end
$var parameter 32 #" ACCUMULATION_WIDTH $end
$var parameter 32 $" IFMAP_WIDTH $end
$var parameter 34 %" PSUM_WIDTH $end
$var parameter 32 &" WEIGHT_WIDTH $end
$var reg 8 '" ifmap_r [7:0] $end
$var reg 20 (" psum_r [19:0] $end
$upscope $end
$upscope $end
$upscope $end
$scope begin R[2] $end
$var parameter 3 )" r $end
$scope begin C[0] $end
$var parameter 2 *" c $end
$scope module u_PE_weight_stationary $end
$var wire 1 , clk $end
$var wire 8 +" ifmap_i [7:0] $end
$var wire 1 - nrst $end
$var wire 1 / pe_en $end
$var wire 20 ," psum_i [19:0] $end
$var wire 8 -" weight_i [7:0] $end
$var wire 20 ." psum_o [19:0] $end
$var wire 8 /" ifmap_o [7:0] $end
$var parameter 32 0" ACCUMULATION_WIDTH $end
$var parameter 32 1" IFMAP_WIDTH $end
$var parameter 34 2" PSUM_WIDTH $end
$var parameter 32 3" WEIGHT_WIDTH $end
$var reg 8 4" ifmap_r [7:0] $end
$var reg 20 5" psum_r [19:0] $end
$upscope $end
$upscope $end
$scope begin C[1] $end
$var parameter 2 6" c $end
$scope module u_PE_weight_stationary $end
$var wire 1 , clk $end
$var wire 8 7" ifmap_i [7:0] $end
$var wire 1 - nrst $end
$var wire 1 / pe_en $end
$var wire 20 8" psum_i [19:0] $end
$var wire 8 9" weight_i [7:0] $end
$var wire 20 :" psum_o [19:0] $end
$var wire 8 ;" ifmap_o [7:0] $end
$var parameter 32 <" ACCUMULATION_WIDTH $end
$var parameter 32 =" IFMAP_WIDTH $end
$var parameter 34 >" PSUM_WIDTH $end
$var parameter 32 ?" WEIGHT_WIDTH $end
$var reg 8 @" ifmap_r [7:0] $end
$var reg 20 A" psum_r [19:0] $end
$upscope $end
$upscope $end
$scope begin C[2] $end
$var parameter 3 B" c $end
$scope module u_PE_weight_stationary $end
$var wire 1 , clk $end
$var wire 8 C" ifmap_i [7:0] $end
$var wire 1 - nrst $end
$var wire 1 / pe_en $end
$var wire 20 D" psum_i [19:0] $end
$var wire 8 E" weight_i [7:0] $end
$var wire 20 F" psum_o [19:0] $end
$var wire 8 G" ifmap_o [7:0] $end
$var parameter 32 H" ACCUMULATION_WIDTH $end
$var parameter 32 I" IFMAP_WIDTH $end
$var parameter 34 J" PSUM_WIDTH $end
$var parameter 32 K" WEIGHT_WIDTH $end
$var reg 8 L" ifmap_r [7:0] $end
$var reg 20 M" psum_r [19:0] $end
$upscope $end
$upscope $end
$upscope $end
$scope begin genblk1[0] $end
$var parameter 2 N" row $end
$upscope $end
$scope begin genblk1[1] $end
$var parameter 2 O" row $end
$upscope $end
$scope begin genblk1[2] $end
$var parameter 3 P" row $end
$upscope $end
$scope begin genblk2[0] $end
$var parameter 2 Q" col $end
$upscope $end
$scope begin genblk2[1] $end
$var parameter 2 R" col $end
$upscope $end
$scope begin genblk2[2] $end
$var parameter 3 S" col $end
$upscope $end
$scope module u_weight_kernel_conv0 $end
$var wire 72 T" weight_o [71:0] $end
$var parameter 32 U" KERNEL_HEIGHT $end
$var parameter 32 V" KERNEL_WIDTH $end
$var parameter 32 W" WEIGHT_WIDTH $end
$upscope $end
$upscope $end
$scope begin $ivl_for_loop0 $end
$var integer 32 X" i [31:0] $end
$upscope $end
$upscope $end
$enddefinitions $end
$comment Show the parameter values. $end
$dumpall
b1000 W"
b11 V"
b11 U"
b10 S"
b1 R"
b0 Q"
b10 P"
b1 O"
b0 N"
b1000 K"
b10100 J"
b1000 I"
b100 H"
b10 B"
b1000 ?"
b10100 >"
b1000 ="
b100 <"
b1 6"
b1000 3"
b10100 2"
b1000 1"
b100 0"
b0 *"
b10 )"
b1000 &"
b10100 %"
b1000 $"
b100 #"
b10 {
b1000 x
b10100 w
b1000 v
b100 u
b1 o
b1000 l
b10100 k
b1000 j
b100 i
b0 c
b1 b
b1000 _
b10100 ^
b1000 ]
b100 \
b10 V
b1000 S
b10100 R
b1000 Q
b100 P
b1 J
b1000 G
b10100 F
b1000 E
b100 D
b0 >
b0 =
b1000 ;
b11 :
b11 9
b10011 8
b100 7
b1101 6
b1000 5
b1000 +
b11 *
b11 )
b10011 (
b1101 '
b1000 &
$end
#0
$dumpvars
b11 X"
b1000000010000000100000001000000010000000100000001000000010000000100000 T"
b0 M"
b0 L"
b0 G"
b0 F"
b100000 E"
b0 D"
b0 C"
b0 A"
b0 @"
b0 ;"
b0 :"
b100000 9"
b0 8"
b0 7"
b0 5"
b0 4"
b0 /"
b0 ."
b100000 -"
b0 ,"
b0 +"
b0 ("
b0 '"
b0 ""
b0 !"
b100000 ~
b0 }
b0 |
b0 z
b0 y
b0 t
b0 s
b100000 r
b0 q
b0 p
b0 n
b0 m
b0 h
b0 g
b100000 f
b0 e
b0 d
b0 a
b0 `
b0 [
b0 Z
b100000 Y
b0 X
b0 W
b0 U
b0 T
b0 O
b0 N
b100000 M
b0 L
b0 K
b0 I
b0 H
b0 C
b0 B
b100000 A
b0 @
b0 ?
b0 <
b0 4
b0 3
b0 2
b1000000010000000100000001000000010000000100000001000000010000000100000 1
b0 0
0/
b0 .
0-
1,
b0 %
b0 $
b0 #
b0 "
0!
$end
#1000
1-
#5000
0,
#10000
1,
#15000
0,
#20000
1,
#25000
0,
#30000
1,
#31000
b11 ?
b11 4
b11 .
b11 0
1/
#35000
0,
#40000
b1100000 e
b1100000000000000000000000000000000000000000000000000000000000000 2
b11 K
b1100000 B
b1100000 I
b1100000011 4
b11 C
b11 H
b1 <
1,
#41000
b10 d
b1000000000000000000000001100000011 4
b1000000011 .
b1000000011 0
#45000
0,
#50000
b10100000 ,"
b1100000 q
b10 p
b11 W
b10100000000000000000000000000000000000011000000000000000001100000000000000000000000000000000000000000000000000000000000000 2
b10 <
b10 h
b10 m
b10100000 g
b10100000 n
b100000001000000000000000110000001100000011 4
b11 O
b11 T
b1100000 N
b1100000 U
1,
#51000
b1 +"
b10000000000000000000000100000001000000000000000110000001100000011 4
b10000001000000011 .
b10000001000000011 0
#55000
0,
#60000
b11000000 $
b1100000 }
b10100000 8"
b11000000 %
b11000000 3
b10 |
b11000000000000000000000000000000000000101000000000000000010100000000000000000110000000000000000011000000000000000001100000000000000000000000000000000000000000000000000000000000000 2
b1 7"
b1100000 Z
b1100000 a
b11 [
b11 `
b10100000 s
b10100000 z
b10 t
b10 y
b11000000 ."
b11000000 5"
b1000000010000000000000010000000100000001000000011000000110000001100000011 4
b1 /"
b1 4"
b11 <
1,
#65000
0,
#70000
b11000000 #
b110000000000000000011000000 %
b110000000000000000011000000 3
b10100000 D"
b1 C"
b110000000000000000011000000000000000001010000000000000000101000000000000000010100000000000000000110000000000000000011000000000000000001100000000000000000000000000000000000000000000000000000000000000 2
b100 <
b1 ;"
b1 @"
b11000000 :"
b11000000 A"
b100000001000000010000001000000010000000100000001000000011000000110000001100000011 4
b10 ""
b10 '"
b10100000 !"
b10100000 ("
1,
#75000
0,
#80000
b11000000 "
b1100000000000000000110000000000000000011000000 %
b1100000000000000000110000000000000000011000000 3
1!
b1100000000000000000110000000000000000011000000000000000001010000000000000000101000000000000000010100000000000000000110000000000000000011000000000000000001100000000000000000000000000000000000000000000000000000000000000 2
b11000000 F"
b11000000 M"
b10000000100000001000000010000001000000010000000100000001000000011000000110000001100000011 4
b1 G"
b1 L"
b101 <
1,
#85000
0,
#90000
b110 <
1,
#95000
0,
#100000
b111 <
1,
#105000
0,
#110000
b1000 <
1,
#111000
b0 ?
b10000000100000001000000010000001000000010000000100000001000000011000000110000001100000000 4
b10000001000000000 .
b10000001000000000 0
#115000
0,
#120000
b0 e
b1100000000000000000110000000000000000011000000000000000001010000000000000000101000000000000000010100000000000000000110000000000000000011000000000000000000000000000000000000000000000000000000000000000000000000000000000 2
b0 K
b0 B
b0 I
b10000000100000001000000010000001000000010000000100000001000000011000000110000000000000000 4
b0 C
b0 H
b1001 <
1,
#121000
b0 d
b10000000100000001000000010000001000000010000000100000000000000011000000110000000000000000 4
b10000000000000000 .
b10000000000000000 0
#125000
0,
#130000
b0 ,"
b0 q
b0 p
b0 W
b1100000000000000000110000000000000000011000000000000000001010000000000000000101000000000000000000000000000000000000110000000000000000000000000000000000000000000000000000000000000000000000000000000000000000000000000000 2
b1010 <
b0 h
b0 m
b0 g
b0 n
b10000000100000001000000010000001000000010000000000000000000000011000000000000000000000000 4
b0 O
b0 T
b0 N
b0 U
1,
#131000
b0 +"
b10000000100000001000000000000001000000010000000000000000000000011000000000000000000000000 4
b0 .
b0 0
0/
#135000
0,
#140000
b0 $
b0 #
b0 "
b0 }
b0 8"
b0 D"
b0 %
b0 3
0!
b0 |
b0 7"
b0 C"
b0 2
b0 Z
b0 a
b0 [
b0 `
b0 s
b0 z
b0 t
b0 y
b0 !"
b0 ("
b0 ""
b0 '"
b0 ."
b0 5"
b0 /"
b0 4"
b0 :"
b0 A"
b0 ;"
b0 @"
b0 F"
b0 M"
b0 4
b0 G"
b0 L"
b0 <
1,
