src/spi_host.sv
`default_nettype none

// load data_length, and en high one period
// then load value in the interface
// send data 
module spi_host #(
    parameter DATA_WIDTH = 8,// output 1 byte(8-bit) at one spi_clk cycle
    parameter BIT_DUR = 2,
    parameter BYTE_STORE = 250 // maximum store data in interface before send data
)( 
    input wire clk, 
    input wire nrst,
    //input wire en,
    //input wire [7:0] data_length,

    input wire load_iv,
    input wire [DATA_WIDTH-1:0] load_id,
    
    output logic clk_out,
    output logic sel_out,
    output logic [DATA_WIDTH-1:0] data_out
);

    localparam IDLE = 0;
    localparam START = 1;
    localparam LOAD = 2;
    localparam SEND = 3;

    localparam CNT_WIDTH = $clog2(BYTE_STORE);

    logic [1:0] state;
    logic [DATA_WIDTH*BYTE_STORE-1:0] data_buf;

    logic [CNT_WIDTH-1:0] load_cnt;
    logic finish_load;

    logic [CNT_WIDTH-1:0] send_cnt;
    logic [BIT_DUR-1:0] clk_cnt;
    logic finish_send;

    always_ff @(posedge clk or negedge nrst) begin
        if(~nrst) state <= IDLE;
        //else if((state==IDLE) && en) state <= START;
        //else if(state==START) state <= LOAD;
        else if((state==IDLE) && load_iv) state <= LOAD;
        else if((state==LOAD) && finish_load) state <= SEND;
        else if((state==SEND) && finish_send) state <= IDLE;
        else state <= state;
    end

    // // store length
    // always_ff @(posedge clk or negedge nrst) begin
    //     if(~nrst) load_cnt <= 0;
    //     else if(state==START) load_cnt <= data_length;
    //     else if(state==IDLE)  load_cnt <= 0;
    //     else load_cnt <= load_cnt;
    // end

    // data load
    assign finish_load = (state==LOAD) && ~load_iv;
    always_ff @(posedge clk or negedge nrst) begin
        if(~nrst) load_cnt <= 0;
        else if((state==LOAD) && load_iv) load_cnt <= load_cnt + 1;
        else if(state==IDLE) load_cnt <= 0;
        else load_cnt <= load_cnt;
    end

    // send 
    always_ff @(posedge clk or negedge nrst) begin
        if(~nrst) sel_out <= 1;
        else if((state==LOAD) && finish_load) sel_out <= 0;
        else if(state==SEND) sel_out <= (finish_send) ? 1 : 0;
        else sel_out <= 1;
    end

    always_ff @(posedge clk or negedge nrst) begin
        if(~nrst) begin
            clk_cnt <= 0;
            clk_out <= 1;
        end
        else if((state==LOAD) && finish_load) begin
            clk_cnt <= 0;
            clk_out <= 0;
        end
        else if(state==SEND) begin
            clk_cnt <= clk_cnt + 1;
            clk_out <= (~finish_send && ((clk_cnt=={(BIT_DUR-1){1'b1}}) || (clk_cnt=={BIT_DUR{1'b1}}))) ? ~clk_out : clk_out;
        end
        else begin
            clk_cnt <= 0;
            clk_out <= 1;
        end
    end

    assign finish_send = (send_cnt==load_cnt) && (clk_cnt=={BIT_DUR{1'b1}});
    always_ff @(posedge clk or negedge nrst) begin
        if(~nrst) send_cnt <= 0;
        else if((state==SEND) && (send_cnt<load_cnt)) send_cnt <= (clk_cnt=={BIT_DUR{1'b1}}) ? (send_cnt+1) : send_cnt;
        else if((state==SEND) && (send_cnt==load_cnt)) send_cnt <= (clk_cnt=={BIT_DUR{1'b1}}) ? 0 : send_cnt;
        else send_cnt <= 0;
    end

    // load data during LOAD, pip data at SEND
    assign data_out = data_buf[DATA_WIDTH-1:0];
    always_ff @(posedge clk or negedge nrst) begin
        if(~nrst) data_buf <= 0;
        else if(state==LOAD) data_buf <= (load_iv) ? {data_buf, load_id} : data_buf;
        else if(state==SEND) data_buf <= (clk_cnt=={BIT_DUR{1'b1}}) ? data_buf >> DATA_WIDTH : data_buf;
        else data_buf <= 0;
    end

endmodule


// module spi_gen #(parameter MESSAGE_WIDTH = 8,
//                     parameter BIT_DUR = 2)
//                   ( input wire clk_in, input wire rst_in,
//                     input wire [MESSAGE_WIDTH-1:0]msg_in,
//                     input wire trigger_in,
//                     output logic data_out,
//                     output logic clk_out,
//                     output logic sel_out);
    
//     logic [MESSAGE_WIDTH-1:0] msg_reg;
//     logic [BIT_DUR-1:0] clk_cnt;
//     logic [MESSAGE_WIDTH-1:0] msg_cnt;
//     logic finish;

//     assign data_out = msg_reg[MESSAGE_WIDTH-1];

//     always_ff @(posedge clk_in) begin
//         if(rst_in) begin
//             clk_out  <= 1'b1;
//             sel_out  <= 1'b1;
//             msg_reg  <= {MESSAGE_WIDTH{1'b1}};
//             msg_cnt  <= {MESSAGE_WIDTH{1'b1}};
//             clk_cnt  <= {BIT_DUR{1'b0}};
//             finish   <= 1'b0;
//         end
//         else if(trigger_in) begin
//             clk_cnt <= 1'b0;
//             msg_reg <= msg_in; // one clk
//             msg_cnt <= {1'b0, msg_cnt[MESSAGE_WIDTH-2:0]};
//             finish  <= 1'b0;

//             sel_out <= 1'b0;
//             clk_out <= 1'b0;
//         end
//         else if(~finish && ~sel_out) begin
//             sel_out  <= 1'b0;
//             finish   <= ((|msg_cnt==1'b0) && (clk_cnt=={BIT_DUR{1'b1}}-1'b1)) ? 1'b1 : 1'b0;
//             if(BIT_DUR > 1) clk_out  <= ((clk_cnt== {(BIT_DUR-1){1'b1}}) || (clk_cnt=={BIT_DUR{1'b1}}))? ~clk_out : clk_out;
//             else            clk_out  <= ((clk_cnt== 1'b0) || (clk_cnt=={BIT_DUR{1'b1}}))? ~clk_out : clk_out;
//             msg_reg  <= (clk_cnt == {BIT_DUR{1'b1}}) ? {msg_reg[MESSAGE_WIDTH-2:0], 1'b0} : msg_reg;
//             msg_cnt  <= (clk_cnt == {BIT_DUR{1'b1}}) ? {1'b0, msg_cnt[MESSAGE_WIDTH-1:1]} : msg_cnt;
//             clk_cnt  <= clk_cnt + 1'b1;
//         end
//         else if(finish) begin
//             clk_out  <= 1'b1;
//             sel_out  <= 1'b1;
//             finish   <= 1'b0;

//             msg_reg  <= {MESSAGE_WIDTH{1'b1}};
//             msg_cnt  <= {MESSAGE_WIDTH{1'b1}};
//             clk_cnt  <= {BIT_DUR{1'b0}};
//         end
//         else begin
//             clk_out  <= 1'b1;
//             sel_out  <= 1'b1;

//             finish   <= 1'b0;
//             msg_reg  <= {MESSAGE_WIDTH{1'b1}};
//             msg_cnt  <= {MESSAGE_WIDTH{1'b1}};
//             clk_cnt  <= {BIT_DUR{1'b0}};
//         end
//     end
// endmodule


// `default_nettype wire

sim/tb_spi_host.sv
`default_nettype none

module tb_spi_host;

    parameter DATA_WIDTH = 8;// output 1 byte(8-bit) at one spi_clk cycle
    parameter BIT_DUR = 2;
    parameter BYTE_STORE = 250; // maximum store data in interface before send data

    logic clk;
    logic nrst;
    logic en;
    //logic [7:0] data_length;

    logic load_iv;
    logic [DATA_WIDTH-1:0] load_id;
    
    logic clk_out;
    logic sel_out;
    logic [DATA_WIDTH-1:0] data_out;

    spi_host#(
        .DATA_WIDTH    ( 8 ),
        .BIT_DUR       ( 2 ),
        .BYTE_STORE    ( 20 )
    )u_spi_host(
        .clk         ( clk           ),
        .nrst        ( nrst          ),
        //.en          ( en            ),
        //.data_length ( data_length   ),
        .load_iv     ( load_iv       ),
        .load_id     ( load_id       ),
        .clk_out     ( clk_out ),
        .sel_out     ( sel_out ),
        .data_out    ( data_out  )
    );

    always begin
        #5 clk = ~clk;
    end

    initial begin
        $display("Starting Sim"); //print nice message
        $dumpfile("sim/vcd/spi_host.vcd"); //file to store value change dump (vcd)
        $dumpvars(0,tb_spi_host); //store everything at the current level and below
        $display("Testing assorted values");
        
        // initialize
        clk = 1;  nrst = 0;
        en = 0;   load_iv = 0;
        load_id = 0;
        #1;
        #10 nrst = 1;
        #10 en = 1;
        #10 en = 0;

        #10;
        #10 load_iv = 1;
        for(int i=1; i<15; i=i+1) begin
            #10 load_id = i;
        end
        #10 load_iv = 0;

        #5000;
        
        $display("Finishing Sim"); //print nice message
        $finish;
    end

endmodule 

`default_nettype wire

sim/vcd/spi_host.vcd
$date
	Sun Nov 13 15:46:12 2022
$end
$version
	Icarus Verilog
$end
$timescale
	1s
$end
$scope module tb_spi_host $end
$var wire 1 ! sel_out $end
$var wire 8 " data_out [7:0] $end
$var wire 1 # clk_out $end
$var parameter 32 $ BIT_DUR $end
$var parameter 32 % BYTE_STORE $end
$var parameter 32 & DATA_WIDTH $end
$var reg 1 ' clk $end
$var reg 1 ( en $end
$var reg 8 ) load_id [7:0] $end
$var reg 1 * load_iv $end
$var reg 1 + nrst $end
$scope module u_spi_host $end
$var wire 1 ' clk $end
$var wire 1 , finish_load $end
$var wire 1 - finish_send $end
$var wire 8 . load_id [7:0] $end
$var wire 1 * load_iv $end
$var wire 1 + nrst $end
$var wire 8 / data_out [7:0] $end
$var parameter 32 0 BIT_DUR $end
$var parameter 32 1 BYTE_STORE $end
$var parameter 32 2 CNT_WIDTH $end
$var parameter 32 3 DATA_WIDTH $end
$var parameter 32 4 IDLE $end
$var parameter 32 5 LOAD $end
$var parameter 32 6 SEND $end
$var parameter 32 7 START $end
$var reg 2 8 clk_cnt [1:0] $end
$var reg 1 # clk_out $end
$var reg 160 9 data_buf [159:0] $end
$var reg 5 : load_cnt [4:0] $end
$var reg 1 ! sel_out $end
$var reg 5 ; send_cnt [4:0] $end
$var reg 2 < state [1:0] $end
$upscope $end
$scope begin $ivl_for_loop0 $end
$var integer 32 = i [31:0] $end
$upscope $end
$upscope $end
$enddefinitions $end
$comment Show the parameter values. $end
$dumpall
b1 7
b11 6
b10 5
b0 4
b1000 3
b101 2
b10100 1
b10 0
b1000 &
b11111010 %
b10 $
$end
#0
$dumpvars
b0 =
b0 <
b0 ;
b0 :
b0 9
b0 8
b0 /
b0 .
0-
0,
0+
0*
b0 )
0(
1'
1#
b0 "
1!
$end
#5
0'
#10
1'
#11
1+
#15
0'
#20
1'
#21
1(
#25
0'
#30
1'
#31
0(
#35
0'
#40
1'
#45
0'
#50
1'
#51
b1 =
1*
#55
0'
#60
b10 <
1'
#61
b10 =
b1 )
b1 .
#65
0'
#70
b1 "
b1 /
b1 9
b1 :
1'
#71
b11 =
b10 )
b10 .
#75
0'
#80
b10 "
b10 /
b10 :
b100000010 9
1'
#81
b100 =
b11 )
b11 .
#85
0'
#90
b11 "
b11 /
b10000001000000011 9
b11 :
1'
#91
b101 =
b100 )
b100 .
#95
0'
#100
b100 "
b100 /
b100 :
b1000000100000001100000100 9
1'
#101
b110 =
b101 )
b101 .
#105
0'
#110
b101 "
b101 /
b100000010000000110000010000000101 9
b101 :
1'
#111
b111 =
b110 )
b110 .
#115
0'
#120
b110 "
b110 /
b110 :
b10000001000000011000001000000010100000110 9
1'
#121
b1000 =
b111 )
b111 .
#125
0'
#130
b111 "
b111 /
b1000000100000001100000100000001010000011000000111 9
b111 :
1'
#131
b1001 =
b1000 )
b1000 .
#135
0'
#140
b1000 "
b1000 /
b1000 :
b100000010000000110000010000000101000001100000011100001000 9
1'
#141
b1010 =
b1001 )
b1001 .
#145
0'
#150
b1001 "
b1001 /
b10000001000000011000001000000010100000110000001110000100000001001 9
b1001 :
1'
#151
b1011 =
b1010 )
b1010 .
#155
0'
#160
b1010 "
b1010 /
b1010 :
b1000000100000001100000100000001010000011000000111000010000000100100001010 9
1'
#161
b1100 =
b1011 )
b1011 .
#165
0'
#170
b1011 "
b1011 /
b100000010000000110000010000000101000001100000011100001000000010010000101000001011 9
b1011 :
1'
#171
b1101 =
b1100 )
b1100 .
#175
0'
#180
b1100 "
b1100 /
b1100 :
b10000001000000011000001000000010100000110000001110000100000001001000010100000101100001100 9
1'
#181
b1110 =
b1101 )
b1101 .
#185
0'
#190
b1101 "
b1101 /
b1000000100000001100000100000001010000011000000111000010000000100100001010000010110000110000001101 9
b1101 :
1'
#191
b1111 =
b1110 )
b1110 .
#195
0'
#200
b1110 "
b1110 /
b1110 :
b100000010000000110000010000000101000001100000011100001000000010010000101000001011000011000000110100001110 9
1'
#201
1,
0*
#205
0'
#210
0,
0#
0!
b11 <
1'
#215
0'
#220
b1 8
1'
#225
0'
#230
1#
b10 8
1'
#235
0'
#240
b11 8
1'
#245
0'
#250
b1101 "
b1101 /
b1000000100000001100000100000001010000011000000111000010000000100100001010000010110000110000001101 9
b1 ;
0#
b0 8
1'
#255
0'
#260
b1 8
1'
#265
0'
#270
1#
b10 8
1'
#275
0'
#280
b11 8
1'
#285
0'
#290
b1100 "
b1100 /
b10000001000000011000001000000010100000110000001110000100000001001000010100000101100001100 9
b10 ;
0#
b0 8
1'
#295
0'
#300
b1 8
1'
#305
0'
#310
1#
b10 8
1'
#315
0'
#320
b11 8
1'
#325
0'
#330
b1011 "
b1011 /
b100000010000000110000010000000101000001100000011100001000000010010000101000001011 9
b11 ;
0#
b0 8
1'
#335
0'
#340
b1 8
1'
#345
0'
#350
1#
b10 8
1'
#355
0'
#360
b11 8
1'
#365
0'
#370
b1010 "
b1010 /
b1000000100000001100000100000001010000011000000111000010000000100100001010 9
b100 ;
0#
b0 8
1'
#375
0'
#380
b1 8
1'
#385
0'
#390
1#
b10 8
1'
#395
0'
#400
b11 8
1'
#405
0'
#410
b1001 "
b1001 /
b10000001000000011000001000000010100000110000001110000100000001001 9
b101 ;
0#
b0 8
1'
#415
0'
#420
b1 8
1'
#425
0'
#430
1#
b10 8
1'
#435
0'
#440
b11 8
1'
#445
0'
#450
b1000 "
b1000 /
b100000010000000110000010000000101000001100000011100001000 9
b110 ;
0#
b0 8
1'
#455
0'
#460
b1 8
1'
#465
0'
#470
1#
b10 8
1'
#475
0'
#480
b11 8
1'
#485
0'
#490
b111 "
b111 /
b1000000100000001100000100000001010000011000000111 9
b111 ;
0#
b0 8
1'
#495
0'
#500
b1 8
1'
#505
0'
#510
1#
b10 8
1'
#515
0'
#520
b11 8
1'
#525
0'
#530
b110 "
b110 /
b10000001000000011000001000000010100000110 9
b1000 ;
0#
b0 8
1'
#535
0'
#540
b1 8
1'
#545
0'
#550
1#
b10 8
1'
#555
0'
#560
b11 8
1'
#565
0'
#570
b101 "
b101 /
b100000010000000110000010000000101 9
b1001 ;
0#
b0 8
1'
#575
0'
#580
b1 8
1'
#585
0'
#590
1#
b10 8
1'
#595
0'
#600
b11 8
1'
#605
0'
#610
b100 "
b100 /
b1000000100000001100000100 9
b1010 ;
0#
b0 8
1'
#615
0'
#620
b1 8
1'
#625
0'
#630
1#
b10 8
1'
#635
0'
#640
b11 8
1'
#645
0'
#650
b11 "
b11 /
b10000001000000011 9
b1011 ;
0#
b0 8
1'
#655
0'
#660
b1 8
1'
#665
0'
#670
1#
b10 8
1'
#675
0'
#680
b11 8
1'
#685
0'
#690
b10 "
b10 /
b100000010 9
b1100 ;
0#
b0 8
1'
#695
0'
#700
b1 8
1'
#705
0'
#710
1#
b10 8
1'
#715
0'
#720
b11 8
1'
#725
0'
#730
b1 "
b1 /
b1 9
b1101 ;
0#
b0 8
1'
#735
0'
#740
b1 8
1'
#745
0'
#750
1#
b10 8
1'
#755
0'
#760
b11 8
1'
#765
0'
#770
b0 "
b0 /
b0 9
b1110 ;
0#
b0 8
1'
#775
0'
#780
b1 8
1'
#785
0'
#790
1#
b10 8
1'
#795
0'
#800
1-
b11 8
1'
#805
0'
#810
0-
b0 ;
b0 8
1!
b0 <
1'
#815
0'
#820
b0 :
1'
