src/spi_slave.sv
`default_nettype none

module spi_slave #(
    parameter DATA_WIDTH = 8,// output 1 byte(8-bit) at one spi_clk cycle
    parameter BIT_DUR = 2,
    parameter BYTE_STORE = 250 // maximum store data in interface before send data
)( 
    input wire clk, 
    input wire nrst,
    
    input wire clk_in,
    input wire sel_in,
    input wire [DATA_WIDTH-1:0] data_in,

    output logic spi_ov,
    output logic [DATA_WIDTH-1:0] spi_od 
);

    localparam IDLE = 0;
    localparam RECE = 1;
    localparam PIPE = 2;

    localparam CNT_WIDTH = $clog2(BYTE_STORE);

    logic [1:0] state;
    logic finish_rece;
    logic finish_send;

    logic [CNT_WIDTH-1:0] length;
    logic [DATA_WIDTH*BYTE_STORE-1:0] data_buf;
    logic [CNT_WIDTH-1:0] send_cnt;

    logic d_clk_in;
    logic clk_in_posedge;
    always_ff @(posedge clk) begin
        d_clk_in <= clk_in;
    end
    assign clk_in_posedge = ({d_clk_in, clk_in}==2'b01) ? 1'b1 : 1'b0;

    assign finish_rece = clk_in && sel_in;
    always_ff @(posedge clk or negedge nrst) begin
        if(~nrst) state <= IDLE;
        else if((state==IDLE) && ~sel_in) state <= RECE;
        else if((state==RECE) && finish_rece) state <= PIPE;
        else if((state==PIPE) && finish_send) state <= IDLE;
        else state <= state; 
    end

    always_ff @(posedge clk or negedge nrst) begin
        if(~nrst) length <= 0;
        else if((state==RECE) && clk_in_posedge) length <= length + 1;
        else if(state==IDLE) length <= 0;
        else length <= length;
    end

    assign finish_send = (state==PIPE) && (send_cnt==length-1);
    always_ff @(posedge clk or negedge nrst) begin
        if(~nrst) send_cnt <= 0;
        else if((state==PIPE) && (send_cnt<length)) send_cnt <= send_cnt + 1;
        else if((state==PIPE) && (send_cnt==length)) send_cnt <= 0;
        else send_cnt <= 0;
    end

    assign spi_od = data_buf[DATA_WIDTH-1:0];
    assign spi_ov = (state==PIPE);
    always_ff @(posedge clk or negedge nrst) begin
        if(~nrst) data_buf <= 0;
        else if(state==RECE) data_buf <= clk_in_posedge ? {data_buf, data_in} : data_buf;
        else if(state==PIPE) data_buf <= data_buf >> DATA_WIDTH;
        else data_buf <= 0;
    end

endmodule

`default_nettype wire

src/spi_host.sv
`default_nettype none

// load data_length, and en high one period
// then load value in the interface
// send data 
module spi_host #(
    parameter DATA_WIDTH = 8,// output 1 byte(8-bit) at one spi_clk cycle
    parameter BIT_DUR = 2,
    parameter BYTE_STORE = 250 // maximum store data in interface before send data
)( 
    input wire clk, 
    input wire nrst,
    //input wire en,
    //input wire [7:0] data_length,

    input wire load_iv,
    input wire [DATA_WIDTH-1:0] load_id,
    
    output logic clk_out,
    output logic sel_out,
    output logic [DATA_WIDTH-1:0] data_out
);

    localparam IDLE = 0;
    localparam START = 1;
    localparam LOAD = 2;
    localparam SEND = 3;

    localparam CNT_WIDTH = $clog2(BYTE_STORE);

    logic [1:0] state;
    logic [DATA_WIDTH*BYTE_STORE-1:0] data_buf;

    logic [CNT_WIDTH-1:0] load_cnt;
    logic finish_load;

    logic [CNT_WIDTH-1:0] send_cnt;
    logic [BIT_DUR-1:0] clk_cnt;
    logic finish_send;

    always_ff @(posedge clk or negedge nrst) begin
        if(~nrst) state <= IDLE;
        //else if((state==IDLE) && en) state <= START;
        //else if(state==START) state <= LOAD;
        else if((state==IDLE) && load_iv) state <= LOAD;
        else if((state==LOAD) && finish_load) state <= SEND;
        else if((state==SEND) && finish_send) state <= IDLE;
        else state <= state;
    end

    // // store length
    // always_ff @(posedge clk or negedge nrst) begin
    //     if(~nrst) load_cnt <= 0;
    //     else if(state==START) load_cnt <= data_length;
    //     else if(state==IDLE)  load_cnt <= 0;
    //     else load_cnt <= load_cnt;
    // end

    // data load
    assign finish_load = (state==LOAD) && ~load_iv;
    always_ff @(posedge clk or negedge nrst) begin
        if(~nrst) load_cnt <= 0;
        else if((state==LOAD) && load_iv) load_cnt <= load_cnt + 1;
        else if(state==IDLE) load_cnt <= 0;
        else load_cnt <= load_cnt;
    end

    // send 
    always_ff @(posedge clk or negedge nrst) begin
        if(~nrst) sel_out <= 1;
        else if((state==LOAD) && finish_load) sel_out <= 0;
        else if(state==SEND) sel_out <= (finish_send) ? 1 : 0;
        else sel_out <= 1;
    end

    always_ff @(posedge clk or negedge nrst) begin
        if(~nrst) begin
            clk_cnt <= 0;
            clk_out <= 1;
        end
        else if((state==LOAD) && finish_load) begin
            clk_cnt <= 0;
            clk_out <= 0;
        end
        else if(state==SEND) begin
            clk_cnt <= clk_cnt + 1;
            clk_out <= (~finish_send && ((clk_cnt=={(BIT_DUR-1){1'b1}}) || (clk_cnt=={BIT_DUR{1'b1}}))) ? ~clk_out : clk_out;
        end
        else begin
            clk_cnt <= 0;
            clk_out <= 1;
        end
    end

    assign finish_send = (send_cnt==load_cnt) && (clk_cnt=={BIT_DUR{1'b1}});
    always_ff @(posedge clk or negedge nrst) begin
        if(~nrst) send_cnt <= 0;
        else if((state==SEND) && (send_cnt<load_cnt)) send_cnt <= (clk_cnt=={BIT_DUR{1'b1}}) ? (send_cnt+1) : send_cnt;
        else if((state==SEND) && (send_cnt==load_cnt)) send_cnt <= (clk_cnt=={BIT_DUR{1'b1}}) ? 0 : send_cnt;
        else send_cnt <= 0;
    end

    // load data during LOAD, pip data at SEND
    assign data_out = data_buf[DATA_WIDTH-1:0];
    always_ff @(posedge clk or negedge nrst) begin
        if(~nrst) data_buf <= 0;
        else if(state==LOAD) data_buf <= (load_iv) ? {data_buf, load_id} : data_buf;
        else if(state==SEND) data_buf <= (clk_cnt=={BIT_DUR{1'b1}}) ? data_buf >> DATA_WIDTH : data_buf;
        else data_buf <= 0;
    end

endmodule


// module spi_gen #(parameter MESSAGE_WIDTH = 8,
//                     parameter BIT_DUR = 2)
//                   ( input wire clk_in, input wire rst_in,
//                     input wire [MESSAGE_WIDTH-1:0]msg_in,
//                     input wire trigger_in,
//                     output logic data_out,
//                     output logic clk_out,
//                     output logic sel_out);
    
//     logic [MESSAGE_WIDTH-1:0] msg_reg;
//     logic [BIT_DUR-1:0] clk_cnt;
//     logic [MESSAGE_WIDTH-1:0] msg_cnt;
//     logic finish;

//     assign data_out = msg_reg[MESSAGE_WIDTH-1];

//     always_ff @(posedge clk_in) begin
//         if(rst_in) begin
//             clk_out  <= 1'b1;
//             sel_out  <= 1'b1;
//             msg_reg  <= {MESSAGE_WIDTH{1'b1}};
//             msg_cnt  <= {MESSAGE_WIDTH{1'b1}};
//             clk_cnt  <= {BIT_DUR{1'b0}};
//             finish   <= 1'b0;
//         end
//         else if(trigger_in) begin
//             clk_cnt <= 1'b0;
//             msg_reg <= msg_in; // one clk
//             msg_cnt <= {1'b0, msg_cnt[MESSAGE_WIDTH-2:0]};
//             finish  <= 1'b0;

//             sel_out <= 1'b0;
//             clk_out <= 1'b0;
//         end
//         else if(~finish && ~sel_out) begin
//             sel_out  <= 1'b0;
//             finish   <= ((|msg_cnt==1'b0) && (clk_cnt=={BIT_DUR{1'b1}}-1'b1)) ? 1'b1 : 1'b0;
//             if(BIT_DUR > 1) clk_out  <= ((clk_cnt== {(BIT_DUR-1){1'b1}}) || (clk_cnt=={BIT_DUR{1'b1}}))? ~clk_out : clk_out;
//             else            clk_out  <= ((clk_cnt== 1'b0) || (clk_cnt=={BIT_DUR{1'b1}}))? ~clk_out : clk_out;
//             msg_reg  <= (clk_cnt == {BIT_DUR{1'b1}}) ? {msg_reg[MESSAGE_WIDTH-2:0], 1'b0} : msg_reg;
//             msg_cnt  <= (clk_cnt == {BIT_DUR{1'b1}}) ? {1'b0, msg_cnt[MESSAGE_WIDTH-1:1]} : msg_cnt;
//             clk_cnt  <= clk_cnt + 1'b1;
//         end
//         else if(finish) begin
//             clk_out  <= 1'b1;
//             sel_out  <= 1'b1;
//             finish   <= 1'b0;

//             msg_reg  <= {MESSAGE_WIDTH{1'b1}};
//             msg_cnt  <= {MESSAGE_WIDTH{1'b1}};
//             clk_cnt  <= {BIT_DUR{1'b0}};
//         end
//         else begin
//             clk_out  <= 1'b1;
//             sel_out  <= 1'b1;

//             finish   <= 1'b0;
//             msg_reg  <= {MESSAGE_WIDTH{1'b1}};
//             msg_cnt  <= {MESSAGE_WIDTH{1'b1}};
//             clk_cnt  <= {BIT_DUR{1'b0}};
//         end
//     end
// endmodule


// `default_nettype wire

sim/tb_spi_slave.sv
`default_nettype none

module tb_spi_slave;

    parameter DATA_WIDTH = 8;// output 1 byte(8-bit) at one spi_clk cycle
    parameter BIT_DUR = 2;
    parameter BYTE_STORE = 250; // maximum store data in interface before send data

    logic clk;
    logic nrst;
    logic en;
    //logic [7:0] data_length;

    logic load_iv;
    logic [DATA_WIDTH-1:0] load_id;
    
    logic clk_out;
    logic sel_out;
    logic [DATA_WIDTH-1:0] data_out;

    logic spi_ov;
    logic [DATA_WIDTH-1:0] spi_od;

    spi_host#(
        .DATA_WIDTH    ( 8 ),
        .BIT_DUR       ( 2 ),
        .BYTE_STORE    ( 20 )
    )u_spi_host(
        .clk         ( clk           ),
        .nrst        ( nrst          ),

        .load_iv     ( load_iv       ),
        .load_id     ( load_id       ),
        .clk_out     ( clk_out ),
        .sel_out     ( sel_out ),
        .data_out    ( data_out  )
    );

    spi_slave#(
        .DATA_WIDTH ( 8 ),
        .BIT_DUR    ( 2 ),
        .BYTE_STORE ( 20 )
    )u_spi_slave(
        .clk        ( clk        ),
        .nrst       ( nrst       ),
        .clk_in     ( clk_out     ),
        .sel_in     ( sel_out     ),
        .data_in    ( data_out    ),
        .spi_ov     ( spi_ov     ),
        .spi_od     ( spi_od     )
    );

    always begin
        #5 clk = ~clk;
    end

    initial begin
        $display("Starting Sim"); //print nice message
        $dumpfile("sim/vcd/spi_slave.vcd"); //file to store value change dump (vcd)
        $dumpvars(0,tb_spi_slave); //store everything at the current level and below
        $display("Testing assorted values");
        
        // initialize
        clk = 1;  nrst = 0;
        en = 0;   load_iv = 0;
        load_id = 0;
        #1;
        #10 nrst = 1;
        #10 en = 1;
        #10 en = 0;

        #10;
        #10 load_iv = 1;
        for(int i=1; i<15; i=i+1) begin
            #10 load_id = i;
        end
        #10 load_iv = 0;

        #5000;
        
        $display("Finishing Sim"); //print nice message
        $finish;
    end

endmodule 

`default_nettype wire

sim/vcd/spi_slave.vcd
$date
	Sun Nov 13 21:17:35 2022
$end
$version
	Icarus Verilog
$end
$timescale
	1s
$end
$scope module tb_spi_slave $end
$var wire 1 ! spi_ov $end
$var wire 8 " spi_od [7:0] $end
$var wire 1 # sel_out $end
$var wire 8 $ data_out [7:0] $end
$var wire 1 % clk_out $end
$var parameter 32 & BIT_DUR $end
$var parameter 32 ' BYTE_STORE $end
$var parameter 32 ( DATA_WIDTH $end
$var reg 1 ) clk $end
$var reg 1 * en $end
$var reg 8 + load_id [7:0] $end
$var reg 1 , load_iv $end
$var reg 1 - nrst $end
$scope module u_spi_host $end
$var wire 1 ) clk $end
$var wire 1 . finish_load $end
$var wire 1 / finish_send $end
$var wire 8 0 load_id [7:0] $end
$var wire 1 , load_iv $end
$var wire 1 - nrst $end
$var wire 8 1 data_out [7:0] $end
$var parameter 32 2 BIT_DUR $end
$var parameter 32 3 BYTE_STORE $end
$var parameter 32 4 CNT_WIDTH $end
$var parameter 32 5 DATA_WIDTH $end
$var parameter 32 6 IDLE $end
$var parameter 32 7 LOAD $end
$var parameter 32 8 SEND $end
$var parameter 32 9 START $end
$var reg 2 : clk_cnt [1:0] $end
$var reg 1 % clk_out $end
$var reg 160 ; data_buf [159:0] $end
$var reg 5 < load_cnt [4:0] $end
$var reg 1 # sel_out $end
$var reg 5 = send_cnt [4:0] $end
$var reg 2 > state [1:0] $end
$upscope $end
$scope module u_spi_slave $end
$var wire 1 ) clk $end
$var wire 1 % clk_in $end
$var wire 8 ? data_in [7:0] $end
$var wire 1 @ finish_rece $end
$var wire 1 A finish_send $end
$var wire 1 - nrst $end
$var wire 1 # sel_in $end
$var wire 1 ! spi_ov $end
$var wire 8 B spi_od [7:0] $end
$var wire 1 C clk_in_posedge $end
$var parameter 32 D BIT_DUR $end
$var parameter 32 E BYTE_STORE $end
$var parameter 32 F CNT_WIDTH $end
$var parameter 32 G DATA_WIDTH $end
$var parameter 32 H IDLE $end
$var parameter 32 I PIPE $end
$var parameter 32 J RECE $end
$var reg 1 K d_clk_in $end
$var reg 160 L data_buf [159:0] $end
$var reg 5 M length [4:0] $end
$var reg 5 N send_cnt [4:0] $end
$var reg 2 O state [1:0] $end
$upscope $end
$scope begin $ivl_for_loop0 $end
$var integer 32 P i [31:0] $end
$upscope $end
$upscope $end
$enddefinitions $end
$comment Show the parameter values. $end
$dumpall
b1 J
b10 I
b0 H
b1000 G
b101 F
b10100 E
b10 D
b1 9
b11 8
b10 7
b0 6
b1000 5
b101 4
b10100 3
b10 2
b1000 (
b11111010 '
b10 &
$end
#0
$dumpvars
b0 P
b0 O
b0 N
b0 M
b0 L
xK
xC
b0 B
0A
1@
b0 ?
b0 >
b0 =
b0 <
b0 ;
b0 :
b0 1
b0 0
0/
0.
0-
0,
b0 +
0*
1)
1%
b0 $
1#
b0 "
0!
$end
#5
0)
#10
0C
1K
1)
#11
1-
#15
0)
#20
1)
#21
1*
#25
0)
#30
1)
#31
0*
#35
0)
#40
1)
#45
0)
#50
1)
#51
b1 P
1,
#55
0)
#60
b10 >
1)
#61
b10 P
b1 +
b1 0
#65
0)
#70
b1 $
b1 1
b1 ?
b1 ;
b1 <
1)
#71
b11 P
b10 +
b10 0
#75
0)
#80
b10 $
b10 1
b10 ?
b10 <
b100000010 ;
1)
#81
b100 P
b11 +
b11 0
#85
0)
#90
b11 $
b11 1
b11 ?
b10000001000000011 ;
b11 <
1)
#91
b101 P
b100 +
b100 0
#95
0)
#100
b100 $
b100 1
b100 ?
b100 <
b1000000100000001100000100 ;
1)
#101
b110 P
b101 +
b101 0
#105
0)
#110
b101 $
b101 1
b101 ?
b100000010000000110000010000000101 ;
b101 <
1)
#111
b111 P
b110 +
b110 0
#115
0)
#120
b110 $
b110 1
b110 ?
b110 <
b10000001000000011000001000000010100000110 ;
1)
#121
b1000 P
b111 +
b111 0
#125
0)
#130
b111 $
b111 1
b111 ?
b1000000100000001100000100000001010000011000000111 ;
b111 <
1)
#131
b1001 P
b1000 +
b1000 0
#135
0)
#140
b1000 $
b1000 1
b1000 ?
b1000 <
b100000010000000110000010000000101000001100000011100001000 ;
1)
#141
b1010 P
b1001 +
b1001 0
#145
0)
#150
b1001 $
b1001 1
b1001 ?
b10000001000000011000001000000010100000110000001110000100000001001 ;
b1001 <
1)
#151
b1011 P
b1010 +
b1010 0
#155
0)
#160
b1010 $
b1010 1
b1010 ?
b1010 <
b1000000100000001100000100000001010000011000000111000010000000100100001010 ;
1)
#161
b1100 P
b1011 +
b1011 0
#165
0)
#170
b1011 $
b1011 1
b1011 ?
b100000010000000110000010000000101000001100000011100001000000010010000101000001011 ;
b1011 <
1)
#171
b1101 P
b1100 +
b1100 0
#175
0)
#180
b1100 $
b1100 1
b1100 ?
b1100 <
b10000001000000011000001000000010100000110000001110000100000001001000010100000101100001100 ;
1)
#181
b1110 P
b1101 +
b1101 0
#185
0)
#190
b1101 $
b1101 1
b1101 ?
b1000000100000001100000100000001010000011000000111000010000000100100001010000010110000110000001101 ;
b1101 <
1)
#191
b1111 P
b1110 +
b1110 0
#195
0)
#200
b1110 $
b1110 1
b1110 ?
b1110 <
b100000010000000110000010000000101000001100000011100001000000010010000101000001011000011000000110100001110 ;
1)
#201
1.
0,
#205
0)
#210
0@
0.
0%
0#
b11 >
1)
#215
0)
#220
b1 :
b1 O
0K
1)
#225
0)
#230
1C
1%
b10 :
1)
#235
0)
#240
b1110 "
b1110 B
0C
b11 :
b1 M
b1110 L
1K
1)
#245
0)
#250
b1101 $
b1101 1
b1101 ?
b1000000100000001100000100000001010000011000000111000010000000100100001010000010110000110000001101 ;
b1 =
0%
b0 :
1)
#255
0)
#260
b1 :
0K
1)
#265
0)
#270
1C
1%
b10 :
1)
#275
0)
#280
b1101 "
b1101 B
0C
b11 :
b10 M
b111000001101 L
1K
1)
#285
0)
#290
b1100 $
b1100 1
b1100 ?
b10000001000000011000001000000010100000110000001110000100000001001000010100000101100001100 ;
b10 =
0%
b0 :
1)
#295
0)
#300
b1 :
0K
1)
#305
0)
#310
1C
1%
b10 :
1)
#315
0)
#320
b1100 "
b1100 B
0C
b11 :
b11 M
b11100000110100001100 L
1K
1)
#325
0)
#330
b1011 $
b1011 1
b1011 ?
b100000010000000110000010000000101000001100000011100001000000010010000101000001011 ;
b11 =
0%
b0 :
1)
#335
0)
#340
b1 :
0K
1)
#345
0)
#350
1C
1%
b10 :
1)
#355
0)
#360
b1011 "
b1011 B
0C
b11 :
b100 M
b1110000011010000110000001011 L
1K
1)
#365
0)
#370
b1010 $
b1010 1
b1010 ?
b1000000100000001100000100000001010000011000000111000010000000100100001010 ;
b100 =
0%
b0 :
1)
#375
0)
#380
b1 :
0K
1)
#385
0)
#390
1C
1%
b10 :
1)
#395
0)
#400
b1010 "
b1010 B
0C
b11 :
b101 M
b111000001101000011000000101100001010 L
1K
1)
#405
0)
#410
b1001 $
b1001 1
b1001 ?
b10000001000000011000001000000010100000110000001110000100000001001 ;
b101 =
0%
b0 :
1)
#415
0)
#420
b1 :
0K
1)
#425
0)
#430
1C
1%
b10 :
1)
#435
0)
#440
b1001 "
b1001 B
0C
b11 :
b110 M
b11100000110100001100000010110000101000001001 L
1K
1)
#445
0)
#450
b1000 $
b1000 1
b1000 ?
b100000010000000110000010000000101000001100000011100001000 ;
b110 =
0%
b0 :
1)
#455
0)
#460
b1 :
0K
1)
#465
0)
#470
1C
1%
b10 :
1)
#475
0)
#480
b1000 "
b1000 B
0C
b11 :
b111 M
b1110000011010000110000001011000010100000100100001000 L
1K
1)
#485
0)
#490
b111 $
b111 1
b111 ?
b1000000100000001100000100000001010000011000000111 ;
b111 =
0%
b0 :
1)
#495
0)
#500
b1 :
0K
1)
#505
0)
#510
1C
1%
b10 :
1)
#515
0)
#520
b111 "
b111 B
0C
b11 :
b1000 M
b111000001101000011000000101100001010000010010000100000000111 L
1K
1)
#525
0)
#530
b110 $
b110 1
b110 ?
b10000001000000011000001000000010100000110 ;
b1000 =
0%
b0 :
1)
#535
0)
#540
b1 :
0K
1)
#545
0)
#550
1C
1%
b10 :
1)
#555
0)
#560
b110 "
b110 B
0C
b11 :
b1001 M
b11100000110100001100000010110000101000001001000010000000011100000110 L
1K
1)
#565
0)
#570
b101 $
b101 1
b101 ?
b100000010000000110000010000000101 ;
b1001 =
0%
b0 :
1)
#575
0)
#580
b1 :
0K
1)
#585
0)
#590
1C
1%
b10 :
1)
#595
0)
#600
b101 "
b101 B
0C
b11 :
b1010 M
b1110000011010000110000001011000010100000100100001000000001110000011000000101 L
1K
1)
#605
0)
#610
b100 $
b100 1
b100 ?
b1000000100000001100000100 ;
b1010 =
0%
b0 :
1)
#615
0)
#620
b1 :
0K
1)
#625
0)
#630
1C
1%
b10 :
1)
#635
0)
#640
b100 "
b100 B
0C
b11 :
b1011 M
b111000001101000011000000101100001010000010010000100000000111000001100000010100000100 L
1K
1)
#645
0)
#650
b11 $
b11 1
b11 ?
b10000001000000011 ;
b1011 =
0%
b0 :
1)
#655
0)
#660
b1 :
0K
1)
#665
0)
#670
1C
1%
b10 :
1)
#675
0)
#680
b11 "
b11 B
0C
b11 :
b1100 M
b11100000110100001100000010110000101000001001000010000000011100000110000001010000010000000011 L
1K
1)
#685
0)
#690
b10 $
b10 1
b10 ?
b100000010 ;
b1100 =
0%
b0 :
1)
#695
0)
#700
b1 :
0K
1)
#705
0)
#710
1C
1%
b10 :
1)
#715
0)
#720
b10 "
b10 B
0C
b11 :
b1101 M
b1110000011010000110000001011000010100000100100001000000001110000011000000101000001000000001100000010 L
1K
1)
#725
0)
#730
b1 $
b1 1
b1 ?
b1 ;
b1101 =
0%
b0 :
1)
#735
0)
#740
b1 :
0K
1)
#745
0)
#750
1C
1%
b10 :
1)
#755
0)
#760
b1 "
b1 B
0C
b11 :
b1110 M
b111000001101000011000000101100001010000010010000100000000111000001100000010100000100000000110000001000000001 L
1K
1)
#765
0)
#770
b0 $
b0 1
b0 ?
b0 ;
b1110 =
0%
b0 :
1)
#775
0)
#780
b1 :
0K
1)
#785
0)
#790
1C
1%
b10 :
1)
#795
0)
#800
1/
b0 "
b0 B
0C
b11 :
b1111 M
b11100000110100001100000010110000101000001001000010000000011100000110000001010000010000000011000000100000000100000000 L
1K
1)
#805
0)
#810
0/
1@
b0 =
b0 :
1#
b0 >
1)
#815
0)
#820
b0 <
1!
b10 O
1)
#825
0)
#830
b1 "
b1 B
b111000001101000011000000101100001010000010010000100000000111000001100000010100000100000000110000001000000001 L
b1 N
1)
#835
0)
#840
b10 "
b10 B
b10 N
b1110000011010000110000001011000010100000100100001000000001110000011000000101000001000000001100000010 L
1)
#845
0)
#850
b11 "
b11 B
b11100000110100001100000010110000101000001001000010000000011100000110000001010000010000000011 L
b11 N
1)
#855
0)
#860
b100 "
b100 B
b100 N
b111000001101000011000000101100001010000010010000100000000111000001100000010100000100 L
1)
#865
0)
#870
b101 "
b101 B
b1110000011010000110000001011000010100000100100001000000001110000011000000101 L
b101 N
1)
#875
0)
#880
b110 "
b110 B
b110 N
b11100000110100001100000010110000101000001001000010000000011100000110 L
1)
#885
0)
#890
b111 "
b111 B
b111000001101000011000000101100001010000010010000100000000111 L
b111 N
1)
#895
0)
#900
b1000 "
b1000 B
b1000 N
b1110000011010000110000001011000010100000100100001000 L
1)
#905
0)
#910
b1001 "
b1001 B
b11100000110100001100000010110000101000001001 L
b1001 N
1)
#915
0)
#920
b1010 "
b1010 B
b1010 N
b111000001101000011000000101100001010 L
1)
#925
0)
#930
b1011 "
b1011 B
b1110000011010000110000001011 L
b1011 N
1)
#935
0)
#940
b1100 "
b1100 B
b1100 N
b11100000110100001100 L
1)
#945
0)
#950
b1101 "
b1101 B
b111000001101 L
b1101 N
1)
#955
0)
#960
1A
b1110 "
b1110 B
b1110 N
b1110 L
1)
#965
0)
#970
b0 "
b0 B
0A
b0 L
b1111 N
0!
b0 O
1)
#975
0)
#980
b0 M
b0 N
1)
