mov-gen/src/instruction_decoder.sv
`default_nettype none

`define DECODE_LAYER               4'd0 
`define COMPUTE_GRID	           4'd1
`define DECODE_LAYER_INFO          4'd2
`define COMPUTE_IFMAP	           4'd3
`define SEND_LAYER_INFO	           4'd4
`define LOAD_WEIGHT	               4'd5
`define LOAD_BIAS	               4'd6
`define SEND_SYSTOLIC_DATA	       4'd7
`define SET_IFMAP_O	               4'd8
`define SEND_OPTIMAL_MOVE	       4'd9

// combinational logic 
module instruction_decoder(
    input wire [31:0] instr,

    output logic [7:0] src1_addr,
    output logic [7:0] src2_addr,
    output logic [11:0] immediate, 
    output logic [7:0] rd_addr, // {rd_group, rd_addr[5:0]}

    output logic [2:0] alu_funct,
    output logic [2:0] br_funct,

    output logic pc_sel, // whether increase or branch operation
    output logic jump_sel,
    output logic src2_sel, 
    output logic wrd_sel, // value load from alu or data_mem
    output logic wrd_en, // write back enable

    output logic decode_layer,
    output logic compute_grid,
    output logic decode_layer_info,
    output logic compute_ifmap,
    output logic send_layer_info,
    output logic load_weights,
    output logic load_bias,
    output logic send_systolic_data,
    output logic set_ifmap_o,
    output logic send_optimal_move
);

    localparam ARITHMETIC = 0;
    localparam BRANCH = 1;
    localparam JUMP = 2;
    localparam LOAD = 3;
    localparam SPECIAL = 4;

    // FURTHER CHECK
    logic [2:0] instr_type;
    always_comb begin
        case(instr[27:25])
            3'b000: instr_type = ARITHMETIC;
            3'b010: instr_type = BRANCH;
            3'b001: instr_type = JUMP;
            3'b100: instr_type = LOAD;
            3'b111: instr_type = SPECIAL;
            default: instr_type = ARITHMETIC;
        endcase
    end

    assign {src2_sel, wrd_sel} = instr[28:27];

    always_comb begin
        if(instr_type==SPECIAL) {pc_sel, jump_sel} = 2'b0;
        else {pc_sel, jump_sel} = instr[26:25];
    end

    always_comb begin
        case(instr_type)
            ARITHMETIC: begin
                alu_funct = instr[31:29]; //selected
                br_funct  = 3'b111;     

                src1_addr = {2'b00, 1'b0, instr[22:18]};
                src2_addr = (instr[28]==0) ?  {2'b00, 1'b0, instr[17:13]} : 8'h00;
                immediate = (instr[28]==1) ? instr[17:6] : 0;
                rd_addr   = {instr[24:23], instr[5:0]};
                wrd_en    = 1;
            end
            BRANCH: begin
                alu_funct = 3'b111; 
                br_funct  = instr[31:29]; //selected     

                src1_addr = {2'b00, 1'b0, instr[22:18]};
                src2_addr = {2'b00, 1'b0, instr[17:13]};
                immediate = instr[11:0];
                rd_addr   = 8'h00;
                wrd_en    = 0;
            end
            JUMP: begin
                alu_funct = 3'b111; 
                br_funct  = 3'b111;     

                src1_addr = 8'h00;
                src2_addr = 8'h00;
                immediate = instr[11:0];
                rd_addr   = 8'h00;
                wrd_en    = 0;
            end
            LOAD: begin
                alu_funct = instr[31:29]; //selected
                br_funct  = 3'b111;     

                src1_addr = {2'b00, 1'b0, instr[22:18]};
                src2_addr = (src2_sel==0) ? {2'b00, 1'b0, instr[17:13]} : 0;
                immediate = (instr[28]==1) ? instr[17:6] : 0;
                rd_addr   = {instr[24:23], instr[5:0]};
                wrd_en    = 1;
            end
            default: begin
                alu_funct = 3'b111; 
                br_funct  = 3'b111;     

                src1_addr = 8'h00;
                src2_addr = 8'h00;
                immediate = 0;
                rd_addr   = 8'h00;
                wrd_en    = 0;
            end
        endcase
    end

    always_comb begin
        if(instr_type==SPECIAL) begin
            decode_layer = (instr[9:6]==`DECODE_LAYER) ? 1 : 0;
            compute_grid  = (instr[9:6]==`COMPUTE_GRID) ? 1 : 0;
            decode_layer_info  = (instr[9:6]==`DECODE_LAYER_INFO) ? 1 : 0;
            compute_ifmap = (instr[9:6]==`COMPUTE_IFMAP) ? 1 : 0;
            send_layer_info  = (instr[9:6]==`SEND_LAYER_INFO) ? 1 : 0;
            load_weights  = (instr[9:6]==`LOAD_WEIGHT) ? 1 : 0;
            load_bias  = (instr[9:6]==`LOAD_BIAS) ? 1 : 0;
            send_systolic_data  = (instr[9:6]==`SEND_SYSTOLIC_DATA) ? 1 : 0;
            set_ifmap_o  = (instr[9:6]==`SET_IFMAP_O) ? 1 : 0;
            send_optimal_move = (instr[9:6]==`SEND_OPTIMAL_MOVE) ? 1 : 0;
        end
        else begin
            decode_layer = 0;
            compute_grid  = 0;
            decode_layer_info  = 0;
            compute_ifmap = 0;
            send_layer_info  = 0;
            load_weights  = 0;
            load_bias  = 0;
            send_systolic_data  = 0;
            set_ifmap_o  = 0;
            send_optimal_move = 0;
        end
    end

endmodule

`default_nettype wire

whh_tpu_v1/sim/tb_instr_decoder.sv
`default_nettype none

`define ZERO               5'h00
`define MOVE_TOTAL_NUM	   5'h01
`define MOVE_CURRENT_NUM   5'h02
`define MOVE_CURRENT	   5'h03
`define MOVE_MAX           5'h04
`define MOVE_MAX_VALUE	   5'h05
`define LAYER_NUM_INFO	   5'h06
`define LAYER_TOTAL_NUM	   5'h07
`define LAYER_CURRENT_NUM  5'h08
`define INPUT_HEIGHT	   5'h09
`define INPUT_WIDTH	       5'h0A
`define LAYER_INFO	       5'h0B
`define WEIGHT_HEIGHT	   5'h0C
`define WEIGHT_WIDTH	   5'h0D
`define WEIGHT_START_ADDR  5'h0E
`define BIAS_HEIGHT	       5'h0F
`define BIAS_WIDTH	       5'h10
`define BIAS_START_ADDR	   5'h11
`define IFMAP_HEIGHT       5'h12
`define IFMAP_WIDTH	       5'h13
`define OP	               5'h14
`define WEIGHT_LENGTH      5'h15
`define BIAS_LENGTH	       5'h16
`define DNN_OUT	           5'h17

module tb_instr_decoder;

    logic clk;

    

    logic [31:0] instr;

    logic [7:0] src1_addr;
    logic [7:0] src2_addr;
    logic [11:0] immediate; 
    logic [7:0] rd_addr; // {rd_group, rd_addr[5:0]}

    logic [2:0] alu_funct;
    logic [2:0] br_funct;

    logic pc_sel; // whether increase or branch operation
    logic jump_sel;
    logic src2_sel; 
    logic wrd_sel; // value load from alu or data_mem
    logic wrd_en; // write back enable

    logic decode_layer;
    logic compute_grid;
    logic decode_layer_info;
    logic compute_ifmap;
    logic send_layer_info;
    logic load_weights;
    logic load_bias;
    logic send_systolic_data;
    logic set_ifmap_o;
    logic send_optimal_move;


instruction_decoder u_instruction_decoder(
    .instr              ( instr                    ),
    
    .src1_addr          (  src1_addr         ),
    .src2_addr          (  src2_addr         ),
    .immediate          (  immediate         ),
    .rd_addr            (  rd_addr           ),
    
    .alu_funct          (  alu_funct         ),
    .br_funct           (  br_funct          ),
    .pc_sel             ( pc_sel             ),
    .jump_sel           ( jump_sel           ),
    .src2_sel           ( src2_sel           ),
    .wrd_sel            ( wrd_sel            ),
    .wrd_en             ( wrd_en             ),
    
    .decode_layer       ( decode_layer       ),
    .compute_grid       ( compute_grid       ),
    .decode_layer_info  ( decode_layer_info  ),
    .compute_ifmap      ( compute_ifmap      ),
    .send_layer_info    ( send_layer_info    ),
    .load_weights       ( load_weights       ),
    .load_bias          ( load_bias          ),
    .send_systolic_data ( send_systolic_data ),
    .set_ifmap_o        ( set_ifmap_o        ),
    .send_optimal_move  ( send_optimal_move  )
);


    initial begin
        clk = 1'd1;
        forever 
            #5 clk = ~clk;
    end

    initial begin
        $display("Starting Sim"); //print nice message
        $dumpfile("sim/vcd/id.vcd"); //file to store value change dump (vcd)
        $dumpvars(0,tb_instr_decoder); //store everything at the current level and below
        $display("Testing assorted values");
        instr = 0;
        #10 instr = {3'd1, 6'd0, `WEIGHT_HEIGHT, `WEIGHT_WIDTH, 7'd0, {1'b0,`WEIGHT_LENGTH}};
        #10 instr = {3'd0, 6'b100_000, `ZERO, 12'd1,{1'b0,`LAYER_CURRENT_NUM} };
        #10 instr = {3'b011, 6'b001_000, `LAYER_CURRENT_NUM, `LAYER_TOTAL_NUM, 1'b0, 12'd11};
        #10 instr = {3'b111, 6'b000_111, 11'b0, 12'd201};
        #10 instr = {3'd0, 6'b110_000, `ZERO, 12'h0AB, {1'b0, `LAYER_INFO}};

        #10 instr = {9'b111_111_111, 13'd0, 4'b0110, 6'd0};
        #10 instr = {9'b111_111_111, 13'd0, 4'b0111, 6'd0};
        #10 instr = {9'b111_111_111, 13'd0, 4'b1000, 6'd0};
        #10 instr = {9'b111_111_111, 13'd0, 4'b0010, 6'd0};

        #200;

        $display("Finishing Sim"); //print nice message
        $finish;
    end

endmodule

`default_nettype wire

whh_tpu_v1/sim/vcd/id.vcd
$date
	Thu Dec 08 16:34:01 2022
$end
$version
	Icarus Verilog
$end
$timescale
	1s
$end
$scope module tb_instr_decoder $end
$var wire 1 ! wrd_sel $end
$var wire 1 " wrd_en $end
$var wire 1 # src2_sel $end
$var wire 8 $ src2_addr [7:0] $end
$var wire 8 % src1_addr [7:0] $end
$var wire 1 & set_ifmap_o $end
$var wire 1 ' send_systolic_data $end
$var wire 1 ( send_optimal_move $end
$var wire 1 ) send_layer_info $end
$var wire 8 * rd_addr [7:0] $end
$var wire 1 + pc_sel $end
$var wire 1 , load_weights $end
$var wire 1 - load_bias $end
$var wire 1 . jump_sel $end
$var wire 12 / immediate [11:0] $end
$var wire 1 0 decode_layer_info $end
$var wire 1 1 decode_layer $end
$var wire 1 2 compute_ifmap $end
$var wire 1 3 compute_grid $end
$var wire 3 4 br_funct [2:0] $end
$var wire 3 5 alu_funct [2:0] $end
$var reg 1 6 clk $end
$var reg 32 7 instr [31:0] $end
$scope module u_instruction_decoder $end
$var wire 32 8 instr [31:0] $end
$var wire 1 ! wrd_sel $end
$var wire 1 # src2_sel $end
$var wire 1 + pc_sel $end
$var wire 1 . jump_sel $end
$var parameter 32 9 ARITHMETIC $end
$var parameter 32 : BRANCH $end
$var parameter 32 ; JUMP $end
$var parameter 32 < LOAD $end
$var parameter 32 = SPECIAL $end
$var reg 3 > alu_funct [2:0] $end
$var reg 3 ? br_funct [2:0] $end
$var reg 1 3 compute_grid $end
$var reg 1 2 compute_ifmap $end
$var reg 1 1 decode_layer $end
$var reg 1 0 decode_layer_info $end
$var reg 12 @ immediate [11:0] $end
$var reg 3 A instr_type [2:0] $end
$var reg 1 - load_bias $end
$var reg 1 , load_weights $end
$var reg 8 B rd_addr [7:0] $end
$var reg 1 ) send_layer_info $end
$var reg 1 ( send_optimal_move $end
$var reg 1 ' send_systolic_data $end
$var reg 1 & set_ifmap_o $end
$var reg 8 C src1_addr [7:0] $end
$var reg 8 D src2_addr [7:0] $end
$var reg 1 " wrd_en $end
$upscope $end
$upscope $end
$enddefinitions $end
$comment Show the parameter values. $end
$dumpall
b100 =
b11 <
b10 ;
b1 :
b0 9
$end
#0
$dumpvars
b0 D
b0 C
b0 B
b0 A
b0 @
b111 ?
b0 >
b0 8
b0 7
16
b0 5
b111 4
03
02
01
00
b0 /
0.
0-
0,
0+
b0 *
0)
0(
0'
0&
b0 %
b0 $
0#
1"
0!
$end
#5
06
#10
b10101 *
b10101 B
b1101 $
b1101 D
b1100 %
b1100 C
b1 5
b1 >
16
b100000001100011010000000010101 7
b100000001100011010000000010101 8
#15
06
#20
1#
b1000 *
b1000 B
b1 /
b1 @
b0 $
b0 D
b0 %
b0 C
b0 5
b0 >
16
b10000000000000000000001001000 7
b10000000000000000000001001000 8
#25
06
#30
1+
0#
0"
b0 *
b0 B
b1011 /
b1011 @
b111 $
b111 D
b1000 %
b1000 C
b11 4
b11 ?
b111 5
b111 >
b1 A
16
b1100100001000001110000000001011 7
b1100100001000001110000000001011 8
#35
06
#40
1.
0+
b11001001 /
b11001001 @
b0 $
b0 D
b0 %
b0 C
b111 4
b111 ?
b10 A
16
b11100011100000000000000011001001 7
b11100011100000000000000011001001 8
#45
06
#50
0.
1!
1#
1"
b1011 *
b1011 B
b10101011 /
b10101011 @
b0 5
b0 >
b11 A
16
b11000000000000010101011001011 7
b11000000000000010101011001011 8
#55
06
#60
1.
1+
1-
0"
b0 *
b0 B
b0 /
b0 @
b111 5
b111 >
b100 A
16
b11111111100000000000000110000000 7
b11111111100000000000000110000000 8
#65
06
#70
1'
0-
16
b11111111100000000000000111000000 7
b11111111100000000000000111000000 8
#75
06
#80
1&
0'
16
b11111111100000000000001000000000 7
b11111111100000000000001000000000 8
#85
06
#90
0&
10
16
b11111111100000000000000010000000 7
b11111111100000000000000010000000 8
